{"valores":[{
    "title" : "Indicadores municipales de sostenibilidad: Valor Añadido Bruto del sector agropesquero (%)",
    "entity" : [ {
      "01000" : {
        "title" : "Araba/Álava",
        "values" : [ {
          "2019" : 1.52,
          "2018" : 1.78,
          "2017" : 1.67,
          "2016" : 1.7,
          "2015" : 1.7,
          "2012" : 1.2,
          "2010" : 1.2,
          "2008" : 1.3,
          "2005" : 1.8,
          "2000" : 3.5
        } ]
      }
    }, {
      "48000" : {
        "title" : "Bizkaia",
        "values" : [ {
          "2019" : 0.83,
          "2018" : 0.78,
          "2017" : 0.91,
          "2016" : 0.6,
          "2015" : 0.6,
          "2012" : 0.9,
          "2010" : 0.7,
          "2008" : 0.6,
          "2005" : 0.7,
          "2000" : 1.0
        } ]
      }
    }, {
      "00000" : {
        "title" : "CAE",
        "values" : [ {
          "2019" : 0.88,
          "2018" : 0.87,
          "2017" : 0.96,
          "2016" : 0.8,
          "2015" : 0.8,
          "2012" : 0.9,
          "2010" : 0.7,
          "2008" : 0.7,
          "2005" : 0.9,
          "2000" : 1.4
        } ]
      }
    }, {
      "20000" : {
        "title" : "Gipuzkoa",
        "values" : [ {
          "2019" : 0.65,
          "2018" : 0.58,
          "2017" : 0.68,
          "2016" : 0.6,
          "2015" : 0.6,
          "2012" : 0.7,
          "2010" : 0.6,
          "2008" : 0.5,
          "2005" : 0.8,
          "2000" : 0.9
        } ]
      }
    } ]
  },{
    "region" : [ {
      "01100" : {
        "title" : "Arabako Ibarrak / Valles Alaveses",
        "values" : [ {
          "2019" : 6.5,
          "2018" : 7.02,
          "2017" : 6.73,
          "2016" : 7.1,
          "2015" : 7.4,
          "2012" : 6.3,
          "2010" : 6.8,
          "2008" : 5.1,
          "2005" : 7.5,
          "2000" : 12.2
        } ]
      }
    }, {
      "01200" : {
        "title" : "Arabako Lautada / Llanada Alavesa",
        "values" : [ {
          "2019" : 0.43,
          "2018" : 0.47,
          "2017" : 0.47,
          "2016" : 0.5,
          "2015" : 0.6,
          "2012" : 0.4,
          "2010" : 0.4,
          "2008" : 0.3,
          "2005" : 0.5,
          "2000" : 0.8
        } ]
      }
    }, {
      "01300" : {
        "title" : "Arabako Mendialdea / Montaña Alavesa",
        "values" : [ {
          "2019" : 11.41,
          "2018" : 12.37,
          "2017" : 11.99,
          "2016" : 12.6,
          "2015" : 12.2,
          "2012" : 9.9,
          "2010" : 8.6,
          "2008" : 6.7,
          "2005" : 10.5,
          "2000" : 18.5
        } ]
      }
    }, {
      "48100" : {
        "title" : "Arratia Nerbioi / Arratia-Nervión",
        "values" : [ {
          "2019" : 2.25,
          "2018" : 1.96,
          "2017" : 2.21,
          "2016" : 2.4,
          "2015" : 2.2,
          "2012" : 1.9,
          "2010" : 1.4,
          "2008" : 1.4,
          "2005" : 1.8,
          "2000" : 3.2
        } ]
      }
    }, {
      "20200" : {
        "title" : "Bidasoa Beherea / Bajo Bidasoa",
        "values" : [ {
          "2019" : 1.3,
          "2018" : 1.29,
          "2017" : 1.34,
          "2016" : 1.0,
          "2015" : 1.1,
          "2012" : 1.2,
          "2010" : 0.9,
          "2008" : 0.8,
          "2005" : 0.9,
          "2000" : 1.2
        } ]
      }
    }, {
      "48200" : {
        "title" : "Bilbo Handia / Gran Bilbao",
        "values" : [ {
          "2019" : 0.1,
          "2018" : 0.09,
          "2017" : 0.11,
          "2016" : 0.1,
          "2015" : 0.1,
          "2012" : 0.1,
          "2010" : 0.1,
          "2008" : 0.1,
          "2005" : 0.1,
          "2000" : 0.1
        } ]
      }
    }, {
      "20100" : {
        "title" : "Deba Beherea / Bajo Deba",
        "values" : [ {
          "2019" : 0.59,
          "2018" : 0.47,
          "2017" : 0.59,
          "2016" : 0.5,
          "2015" : 0.4,
          "2012" : 0.4,
          "2010" : 0.4,
          "2008" : 0.4,
          "2005" : 0.6,
          "2000" : 0.7
        } ]
      }
    }, {
      "20300" : {
        "title" : "Debagoiena / Alto Deba",
        "values" : [ {
          "2019" : 0.57,
          "2018" : 0.45,
          "2017" : 0.64,
          "2016" : 0.5,
          "2015" : 0.5,
          "2012" : 0.4,
          "2010" : 0.4,
          "2008" : 0.3,
          "2005" : 0.5,
          "2000" : 0.5
        } ]
      }
    }, {
      "20400" : {
        "title" : "Donostialdea / Donostia-San Sebastián",
        "values" : [ {
          "2019" : 0.22,
          "2018" : 0.17,
          "2017" : 0.18,
          "2016" : 0.2,
          "2015" : 0.2,
          "2012" : 0.3,
          "2010" : 0.2,
          "2008" : 0.2,
          "2005" : 0.4,
          "2000" : 0.4
        } ]
      }
    }, {
      "48300" : {
        "title" : "Durangaldea / Duranguesado",
        "values" : [ {
          "2019" : 0.4,
          "2018" : 0.35,
          "2017" : 0.38,
          "2016" : 0.4,
          "2015" : 0.4,
          "2012" : 0.3,
          "2010" : 0.3,
          "2008" : 0.3,
          "2005" : 0.4,
          "2000" : 0.7
        } ]
      }
    }, {
      "48400" : {
        "title" : "Enkartazioak / Encartaciones",
        "values" : [ {
          "2019" : 3.32,
          "2018" : 3.46,
          "2017" : 3.78,
          "2016" : 3.8,
          "2015" : 3.4,
          "2012" : 3.3,
          "2010" : 2.9,
          "2008" : 2.7,
          "2005" : 3.0,
          "2000" : 5.9
        } ]
      }
    }, {
      "01400" : {
        "title" : "Errioxa Arabarra / Rioja Alavesa",
        "values" : [ {
          "2019" : 12.74,
          "2018" : 14.77,
          "2017" : 12.47,
          "2016" : 12.5,
          "2015" : 11.3,
          "2012" : 5.8,
          "2010" : 5.8,
          "2008" : 10.1,
          "2005" : 12.3,
          "2000" : 29.5
        } ]
      }
    }, {
      "48500" : {
        "title" : "Gernika-Bermeo",
        "values" : [ {
          "2019" : 14.15,
          "2018" : 13.16,
          "2017" : 15.04,
          "2016" : 7.0,
          "2015" : 6.5,
          "2012" : 13.7,
          "2010" : 9.0,
          "2008" : 6.8,
          "2005" : 10.6,
          "2000" : 10.3
        } ]
      }
    }, {
      "20500" : {
        "title" : "Goierri",
        "values" : [ {
          "2019" : 0.61,
          "2018" : 0.5,
          "2017" : 0.71,
          "2016" : 0.6,
          "2015" : 0.7,
          "2012" : 0.6,
          "2010" : 0.7,
          "2008" : 0.6,
          "2005" : 0.9,
          "2000" : 1.2
        } ]
      }
    }, {
      "01500" : {
        "title" : "Gorbeia Inguruak / Estribaciones del Gorbea",
        "values" : [ {
          "2019" : 2.01,
          "2018" : 2.64,
          "2017" : 2.75,
          "2016" : 2.9,
          "2015" : 3.1,
          "2012" : 3.0,
          "2010" : 2.8,
          "2008" : 1.7,
          "2005" : 2.5,
          "2000" : 4.3
        } ]
      }
    }, {
      "01600" : {
        "title" : "Kantauri Arabarra / Cantábrica Alavesa",
        "values" : [ {
          "2019" : 0.94,
          "2018" : 1.23,
          "2017" : 1.36,
          "2016" : 1.3,
          "2015" : 1.4,
          "2012" : 1.2,
          "2010" : 1.4,
          "2008" : 0.8,
          "2005" : 1.4,
          "2000" : 1.8
        } ]
      }
    }, {
      "48600" : {
        "title" : "Markina-Ondarroa",
        "values" : [ {
          "2019" : 6.72,
          "2018" : 5.81,
          "2017" : 6.4,
          "2016" : 6.7,
          "2015" : 6.3,
          "2012" : 5.2,
          "2010" : 6.2,
          "2008" : 5.1,
          "2005" : 6.2,
          "2000" : 7.5
        } ]
      }
    }, {
      "48700" : {
        "title" : "Plentzia-Mungia",
        "values" : [ {
          "2019" : 1.1,
          "2018" : 1.09,
          "2017" : 1.29,
          "2016" : 1.4,
          "2015" : 1.6,
          "2012" : 1.5,
          "2010" : 1.5,
          "2008" : 1.5,
          "2005" : 1.7,
          "2000" : 2.7
        } ]
      }
    }, {
      "20600" : {
        "title" : "Tolosaldea / Tolosa",
        "values" : [ {
          "2019" : 1.01,
          "2018" : 0.86,
          "2017" : 1.1,
          "2016" : 1.0,
          "2015" : 1.1,
          "2012" : 1.1,
          "2010" : 1.2,
          "2008" : 1.2,
          "2005" : 1.8,
          "2000" : 1.8
        } ]
      }
    }, {
      "20700" : {
        "title" : "Urola-Kostaldea / Urola Costa",
        "values" : [ {
          "2019" : 2.22,
          "2018" : 2.12,
          "2017" : 2.49,
          "2016" : 1.9,
          "2015" : 1.9,
          "2012" : 2.2,
          "2010" : 1.7,
          "2008" : 1.5,
          "2005" : 2.1,
          "2000" : 2.3
        } ]
      }
    } ]
  },{
    "municipality" : [ {
      "48001" : {
        "title" : "Abadiño",
        "values" : [ {
          "2019" : 0.24,
          "2018" : 0.21,
          "2017" : 0.2,
          "2016" : 0.2,
          "2015" : 0.2,
          "2012" : 0.2,
          "2010" : 0.2,
          "2008" : 0.2,
          "2005" : 0.2,
          "2000" : 0.8
        } ]
      }
    }, {
      "20001" : {
        "title" : "Abaltzisketa",
        "values" : [ {
          "2019" : 6.47,
          "2018" : 5.61,
          "2017" : 7.02,
          "2016" : 7.7,
          "2015" : 9.7,
          "2012" : 6.6,
          "2010" : 7.1,
          "2008" : 5.5,
          "2005" : 10.2,
          "2000" : 12.0
        } ]
      }
    }, {
      "48002" : {
        "title" : "Abanto y Ciérvana-Abanto Zierbena",
        "values" : [ {
          "2019" : 0.22,
          "2018" : 0.21,
          "2017" : 0.26,
          "2016" : 0.3,
          "2015" : 0.3,
          "2012" : 0.4,
          "2010" : 0.4,
          "2008" : 0.3,
          "2005" : 0.3,
          "2000" : 0.6
        } ]
      }
    }, {
      "20002" : {
        "title" : "Aduna",
        "values" : [ {
          "2019" : 0.53,
          "2018" : 0.48,
          "2017" : 0.67,
          "2016" : 0.6,
          "2015" : 0.7,
          "2012" : 0.6,
          "2010" : 0.4,
          "2008" : 0.4,
          "2005" : 0.5,
          "2000" : 0.5
        } ]
      }
    }, {
      "20016" : {
        "title" : "Aia",
        "values" : [ {
          "2019" : 4.98,
          "2018" : 4.24,
          "2017" : 5.21,
          "2016" : 4.7,
          "2015" : 5.2,
          "2012" : 6.2,
          "2010" : 6.0,
          "2008" : 5.6,
          "2005" : 6.5,
          "2000" : 7.5
        } ]
      }
    }, {
      "20003" : {
        "title" : "Aizarnazabal",
        "values" : [ {
          "2019" : 0.99,
          "2018" : 1.01,
          "2017" : 1.04,
          "2016" : 1.0,
          "2015" : 1.1,
          "2012" : 1.1,
          "2010" : 1.1,
          "2008" : 0.8,
          "2005" : 0.9,
          "2000" : 1.2
        } ]
      }
    }, {
      "48911" : {
        "title" : "Ajangiz",
        "values" : [ {
          "2019" : 0.95,
          "2018" : 0.81,
          "2017" : 0.95,
          "2016" : 1.0,
          "2015" : 0.9,
          "2012" : 1.0,
          "2010" : 0.9,
          "2008" : 1.0,
          "2005" : 1.1,
          "2000" : 1.1
        } ]
      }
    }, {
      "20004" : {
        "title" : "Albiztur",
        "values" : [ {
          "2019" : 4.06,
          "2018" : 3.16,
          "2017" : 4.66,
          "2016" : 4.2,
          "2015" : 4.1,
          "2012" : 2.4,
          "2010" : 2.5,
          "2008" : 2.8,
          "2005" : 4.3,
          "2000" : 5.4
        } ]
      }
    }, {
      "20005" : {
        "title" : "Alegia",
        "values" : [ {
          "2019" : 0.84,
          "2018" : 0.65,
          "2017" : 0.92,
          "2016" : 0.8,
          "2015" : 0.7,
          "2012" : 0.7,
          "2010" : 0.8,
          "2008" : 0.8,
          "2005" : 1.0,
          "2000" : 0.8
        } ]
      }
    }, {
      "01001" : {
        "title" : "Alegría-Dulantzi",
        "values" : [ {
          "2019" : 3.48,
          "2018" : 3.96,
          "2017" : 4.14,
          "2016" : 3.4,
          "2015" : 3.6,
          "2012" : 1.7,
          "2010" : 1.7,
          "2008" : 1.1,
          "2005" : 2.1,
          "2000" : 3.4
        } ]
      }
    }, {
      "20006" : {
        "title" : "Alkiza",
        "values" : [ {
          "2019" : 11.32,
          "2018" : 9.46,
          "2017" : 11.3,
          "2016" : 9.4,
          "2015" : 10.6,
          "2012" : 8.5,
          "2010" : 9.4,
          "2008" : 11.8,
          "2005" : 13.4,
          "2000" : 19.8
        } ]
      }
    }, {
      "48912" : {
        "title" : "Alonsotegi",
        "values" : [ {
          "2019" : 0.74,
          "2018" : 0.72,
          "2017" : 0.81,
          "2016" : 0.8,
          "2015" : 0.6,
          "2012" : 0.5,
          "2010" : 0.5,
          "2008" : 0.3,
          "2005" : 0.3,
          "2000" : 1.2
        } ]
      }
    }, {
      "20906" : {
        "title" : "Altzaga",
        "values" : [ {
          "2019" : 4.95,
          "2018" : 4.7,
          "2017" : 6.39,
          "2016" : 5.4,
          "2015" : 5.5,
          "2012" : 5.1,
          "2010" : 5.5,
          "2008" : 6.0,
          "2005" : 6.5,
          "2000" : 8.1
        } ]
      }
    }, {
      "20007" : {
        "title" : "Altzo",
        "values" : [ {
          "2019" : 1.27,
          "2018" : 1.17,
          "2017" : 1.84,
          "2016" : 1.2,
          "2015" : 1.2,
          "2012" : 1.4,
          "2010" : 1.2,
          "2008" : 1.4,
          "2005" : 1.8,
          "2000" : 2.5
        } ]
      }
    }, {
      "20008" : {
        "title" : "Amezketa",
        "values" : [ {
          "2019" : 1.54,
          "2018" : 1.56,
          "2017" : 2.07,
          "2016" : 1.8,
          "2015" : 1.7,
          "2012" : 2.4,
          "2010" : 3.0,
          "2008" : 3.6,
          "2005" : 6.0,
          "2000" : 6.5
        } ]
      }
    }, {
      "48003" : {
        "title" : "Amorebieta-Etxano",
        "values" : [ {
          "2019" : 0.31,
          "2018" : 0.27,
          "2017" : 0.31,
          "2016" : 0.4,
          "2015" : 0.4,
          "2012" : 0.4,
          "2010" : 0.4,
          "2008" : 0.3,
          "2005" : 0.6,
          "2000" : 0.6
        } ]
      }
    }, {
      "48004" : {
        "title" : "Amoroto",
        "values" : [ {
          "2019" : 3.96,
          "2018" : 4.03,
          "2017" : 4.74,
          "2016" : 5.6,
          "2015" : 5.7,
          "2012" : 4.4,
          "2010" : 3.3,
          "2008" : 2.8,
          "2005" : 3.8,
          "2000" : 3.9
        } ]
      }
    }, {
      "01002" : {
        "title" : "Amurrio",
        "values" : [ {
          "2019" : 0.95,
          "2018" : 1.19,
          "2017" : 1.29,
          "2016" : 1.2,
          "2015" : 1.3,
          "2012" : 1.0,
          "2010" : 1.2,
          "2008" : 0.7,
          "2005" : 1.2,
          "2000" : 1.7
        } ]
      }
    }, {
      "20009" : {
        "title" : "Andoain",
        "values" : [ {
          "2019" : 0.22,
          "2018" : 0.19,
          "2017" : 0.24,
          "2016" : 0.2,
          "2015" : 0.3,
          "2012" : 0.2,
          "2010" : 0.2,
          "2008" : 0.4,
          "2005" : 0.4,
          "2000" : 0.4
        } ]
      }
    }, {
      "20010" : {
        "title" : "Anoeta",
        "values" : [ {
          "2019" : 0.49,
          "2018" : 0.44,
          "2017" : 0.41,
          "2016" : 0.4,
          "2015" : 0.4,
          "2012" : 0.3,
          "2010" : 0.3,
          "2008" : 0.4,
          "2005" : 0.5,
          "2000" : 0.4
        } ]
      }
    }, {
      "20011" : {
        "title" : "Antzuola",
        "values" : [ {
          "2019" : 1.59,
          "2018" : 1.19,
          "2017" : 1.54,
          "2016" : 1.2,
          "2015" : 1.3,
          "2012" : 1.1,
          "2010" : 1.1,
          "2008" : 0.7,
          "2005" : 1.0,
          "2000" : 1.2
        } ]
      }
    }, {
      "48005" : {
        "title" : "Arakaldo",
        "values" : [ {
          "2019" : 3.98,
          "2018" : 3.79,
          "2017" : 4.41,
          "2016" : 4.7,
          "2015" : 4.6,
          "2012" : 2.0,
          "2010" : 1.4,
          "2008" : 1.3,
          "2005" : 1.7,
          "2000" : 3.2
        } ]
      }
    }, {
      "20012" : {
        "title" : "Arama",
        "values" : [ {
          "2019" : 0.34,
          "2018" : 0.39,
          "2017" : 0.46,
          "2016" : 0.4,
          "2015" : 1.5,
          "2012" : 1.5,
          "2010" : 1.3,
          "2008" : 1.1,
          "2005" : 1.0,
          "2000" : 8.0
        } ]
      }
    }, {
      "01003" : {
        "title" : "Aramaio",
        "values" : [ {
          "2019" : 13.82,
          "2018" : 16.49,
          "2017" : 16.35,
          "2016" : 14.3,
          "2015" : 15.8,
          "2012" : 13.7,
          "2010" : 16.8,
          "2008" : 9.4,
          "2005" : 15.5,
          "2000" : 17.3
        } ]
      }
    }, {
      "48006" : {
        "title" : "Arantzazu",
        "values" : [ {
          "2019" : 5.84,
          "2018" : 4.85,
          "2017" : 4.19,
          "2016" : 4.2,
          "2015" : 3.4,
          "2012" : 3.4,
          "2010" : 3.4,
          "2008" : 2.0,
          "2005" : 3.2,
          "2000" : 13.0
        } ]
      }
    }, {
      "48093" : {
        "title" : "Areatza",
        "values" : [ {
          "2019" : 2.44,
          "2018" : 2.21,
          "2017" : 2.29,
          "2016" : 2.5,
          "2015" : 1.9,
          "2012" : 1.6,
          "2010" : 1.2,
          "2008" : 0.5,
          "2005" : 1.4,
          "2000" : 3.4
        } ]
      }
    }, {
      "20013" : {
        "title" : "Aretxabaleta",
        "values" : [ {
          "2019" : 0.48,
          "2018" : 0.38,
          "2017" : 0.53,
          "2016" : 0.4,
          "2015" : 0.4,
          "2012" : 0.3,
          "2010" : 0.4,
          "2008" : 0.3,
          "2005" : 0.5,
          "2000" : 0.5
        } ]
      }
    }, {
      "01006" : {
        "title" : "Armiñón",
        "values" : [ {
          "2019" : 8.13,
          "2018" : 7.24,
          "2017" : 7.39,
          "2016" : 9.2,
          "2015" : 7.3,
          "2012" : 6.6,
          "2010" : 6.5,
          "2008" : 6.0,
          "2005" : 6.0,
          "2000" : 5.3
        } ]
      }
    }, {
      "01037" : {
        "title" : "Arraia-Maeztu",
        "values" : [ {
          "2019" : 12.17,
          "2018" : 13.44,
          "2017" : 13.32,
          "2016" : 12.6,
          "2015" : 10.9,
          "2012" : 10.2,
          "2010" : 6.8,
          "2008" : 6.7,
          "2005" : 8.2,
          "2000" : 16.9
        } ]
      }
    }, {
      "48009" : {
        "title" : "Arrankudiaga",
        "values" : [ {
          "2019" : 1.88,
          "2018" : 1.49,
          "2017" : 1.66,
          "2016" : 2.1,
          "2015" : 2.0,
          "2012" : 2.4,
          "2010" : 1.9,
          "2008" : 1.5,
          "2005" : 1.8,
          "2000" : 2.8
        } ]
      }
    }, {
      "20055" : {
        "title" : "Arrasate/Mondragón",
        "values" : [ {
          "2019" : 0.18,
          "2018" : 0.14,
          "2017" : 0.2,
          "2016" : 0.2,
          "2015" : 0.1,
          "2012" : 0.1,
          "2010" : 0.1,
          "2008" : 0.1,
          "2005" : 0.1,
          "2000" : 0.1
        } ]
      }
    }, {
      "48914" : {
        "title" : "Arratzu",
        "values" : [ {
          "2019" : 12.9,
          "2018" : 11.28,
          "2017" : 12.74,
          "2016" : 13.0,
          "2015" : 13.3,
          "2012" : 12.6,
          "2010" : 8.0,
          "2008" : 11.7,
          "2005" : 12.7,
          "2000" : 7.6
        } ]
      }
    }, {
      "01008" : {
        "title" : "Arratzua-Ubarrundia",
        "values" : [ {
          "2019" : 6.81,
          "2018" : 7.5,
          "2017" : 8.82,
          "2016" : 9.1,
          "2015" : 9.3,
          "2012" : 7.4,
          "2010" : 8.1,
          "2008" : 6.7,
          "2005" : 5.7,
          "2000" : 7.0
        } ]
      }
    }, {
      "48010" : {
        "title" : "Arrieta",
        "values" : [ {
          "2019" : 12.19,
          "2018" : 13.6,
          "2017" : 15.16,
          "2016" : 15.6,
          "2015" : 15.7,
          "2012" : 12.7,
          "2010" : 11.2,
          "2008" : 9.9,
          "2005" : 14.1,
          "2000" : 15.6
        } ]
      }
    }, {
      "48011" : {
        "title" : "Arrigorriaga",
        "values" : [ {
          "2019" : 0.29,
          "2018" : 0.25,
          "2017" : 0.24,
          "2016" : 0.2,
          "2015" : 0.2,
          "2012" : 0.2,
          "2010" : 0.1,
          "2008" : 0.1,
          "2005" : 0.1,
          "2000" : 0.2
        } ]
      }
    }, {
      "48023" : {
        "title" : "Artea",
        "values" : [ {
          "2019" : 1.88,
          "2018" : 1.74,
          "2017" : 1.98,
          "2016" : 2.1,
          "2015" : 2.1,
          "2012" : 1.6,
          "2010" : 1.5,
          "2008" : 2.1,
          "2005" : 5.8,
          "2000" : 11.4
        } ]
      }
    }, {
      "48008" : {
        "title" : "Artzentales",
        "values" : [ {
          "2019" : 13.57,
          "2018" : 13.61,
          "2017" : 12.35,
          "2016" : 11.9,
          "2015" : 9.9,
          "2012" : 11.0,
          "2010" : 10.2,
          "2008" : 9.9,
          "2005" : 12.5,
          "2000" : 21.0
        } ]
      }
    }, {
      "01004" : {
        "title" : "Artziniega",
        "values" : [ {
          "2019" : 1.97,
          "2018" : 2.69,
          "2017" : 2.39,
          "2016" : 2.1,
          "2015" : 2.2,
          "2012" : 2.0,
          "2010" : 2.0,
          "2008" : 1.4,
          "2005" : 2.3,
          "2000" : 3.6
        } ]
      }
    }, {
      "01009" : {
        "title" : "Asparrena",
        "values" : [ {
          "2019" : 1.29,
          "2018" : 1.54,
          "2017" : 1.66,
          "2016" : 2.4,
          "2015" : 3.1,
          "2012" : 3.3,
          "2010" : 2.1,
          "2008" : 2.4,
          "2005" : 3.5,
          "2000" : 5.7
        } ]
      }
    }, {
      "20014" : {
        "title" : "Asteasu",
        "values" : [ {
          "2019" : 1.49,
          "2018" : 1.35,
          "2017" : 1.56,
          "2016" : 1.6,
          "2015" : 2.1,
          "2012" : 2.4,
          "2010" : 3.0,
          "2008" : 2.6,
          "2005" : 4.2,
          "2000" : 3.9
        } ]
      }
    }, {
      "20903" : {
        "title" : "Astigarraga",
        "values" : [ {
          "2019" : 0.2,
          "2018" : 0.16,
          "2017" : 0.16,
          "2016" : 0.1,
          "2015" : 0.1,
          "2012" : 0.1,
          "2010" : 0.1,
          "2008" : 0.2,
          "2005" : 0.3,
          "2000" : 0.7
        } ]
      }
    }, {
      "20015" : {
        "title" : "Ataun",
        "values" : [ {
          "2019" : 7.69,
          "2018" : 6.14,
          "2017" : 7.81,
          "2016" : 7.2,
          "2015" : 7.4,
          "2012" : 8.0,
          "2010" : 7.5,
          "2008" : 7.5,
          "2005" : 10.2,
          "2000" : 12.2
        } ]
      }
    }, {
      "48091" : {
        "title" : "Atxondo",
        "values" : [ {
          "2019" : 1.07,
          "2018" : 0.97,
          "2017" : 0.89,
          "2016" : 0.9,
          "2015" : 0.7,
          "2012" : 0.7,
          "2010" : 0.6,
          "2008" : 0.5,
          "2005" : 0.8,
          "2000" : 1.7
        } ]
      }
    }, {
      "48070" : {
        "title" : "Aulesti",
        "values" : [ {
          "2019" : 8.84,
          "2018" : 7.91,
          "2017" : 8.18,
          "2016" : 8.3,
          "2015" : 6.1,
          "2012" : 4.7,
          "2010" : 3.8,
          "2008" : 3.3,
          "2005" : 5.1,
          "2000" : 9.7
        } ]
      }
    }, {
      "01010" : {
        "title" : "Ayala/Aiara",
        "values" : [ {
          "2019" : 6.11,
          "2018" : 7.8,
          "2017" : 8.48,
          "2016" : 7.9,
          "2015" : 9.2,
          "2012" : 8.0,
          "2010" : 8.2,
          "2008" : 5.1,
          "2005" : 8.7,
          "2000" : 9.8
        } ]
      }
    }, {
      "20017" : {
        "title" : "Azkoitia",
        "values" : [ {
          "2019" : 0.91,
          "2018" : 0.65,
          "2017" : 0.9,
          "2016" : 0.7,
          "2015" : 0.6,
          "2012" : 0.5,
          "2010" : 0.5,
          "2008" : 0.6,
          "2005" : 1.0,
          "2000" : 1.2
        } ]
      }
    }, {
      "20018" : {
        "title" : "Azpeitia",
        "values" : [ {
          "2019" : 0.87,
          "2018" : 0.67,
          "2017" : 0.88,
          "2016" : 0.7,
          "2015" : 0.7,
          "2012" : 0.6,
          "2010" : 0.5,
          "2008" : 0.5,
          "2005" : 0.7,
          "2000" : 0.9
        } ]
      }
    }, {
      "01049" : {
        "title" : "Añana",
        "values" : [ {
          "2019" : 14.71,
          "2018" : 11.83,
          "2017" : 14.74,
          "2016" : 16.0,
          "2015" : 17.1,
          "2012" : 12.3,
          "2010" : 9.6,
          "2008" : 9.4,
          "2005" : 10.5,
          "2000" : 12.9
        } ]
      }
    }, {
      "48012" : {
        "title" : "Bakio",
        "values" : [ {
          "2019" : 2.85,
          "2018" : 2.7,
          "2017" : 3.34,
          "2016" : 4.1,
          "2015" : 4.9,
          "2012" : 4.9,
          "2010" : 4.1,
          "2008" : 3.6,
          "2005" : 5.5,
          "2000" : 8.0
        } ]
      }
    }, {
      "20904" : {
        "title" : "Baliarrain",
        "values" : [ {
          "2019" : 6.83,
          "2018" : 6.24,
          "2017" : 7.19,
          "2016" : 7.2,
          "2015" : 8.2,
          "2012" : 11.4,
          "2010" : 13.7,
          "2008" : 10.1,
          "2005" : 22.9,
          "2000" : 23.6
        } ]
      }
    }, {
      "48090" : {
        "title" : "Balmaseda",
        "values" : [ {
          "2019" : 0.93,
          "2018" : 0.88,
          "2017" : 0.9,
          "2016" : 0.9,
          "2015" : 0.7,
          "2012" : 0.7,
          "2010" : 0.6,
          "2008" : 0.4,
          "2005" : 0.7,
          "2000" : 1.3
        } ]
      }
    }, {
      "48013" : {
        "title" : "Barakaldo",
        "values" : [ {
          "2019" : 0.03,
          "2018" : 0.03,
          "2017" : 0.03,
          "2016" : 0.0,
          "2015" : 0.0,
          "2012" : 0.0,
          "2010" : 0.0,
          "2008" : 0.0,
          "2005" : 0.0,
          "2000" : 0.1
        } ]
      }
    }, {
      "48014" : {
        "title" : "Barrika",
        "values" : [ {
          "2019" : 1.75,
          "2018" : 1.68,
          "2017" : 1.87,
          "2016" : 1.6,
          "2015" : 1.3,
          "2012" : 1.2,
          "2010" : 1.3,
          "2008" : 1.2,
          "2005" : 1.2,
          "2000" : 2.9
        } ]
      }
    }, {
      "01013" : {
        "title" : "Barrundia",
        "values" : [ {
          "2019" : 26.58,
          "2018" : 27.51,
          "2017" : 28.15,
          "2016" : 27.4,
          "2015" : 25.9,
          "2012" : 23.0,
          "2010" : 23.7,
          "2008" : 19.5,
          "2005" : 25.6,
          "2000" : 30.3
        } ]
      }
    }, {
      "48015" : {
        "title" : "Basauri",
        "values" : [ {
          "2019" : 0.03,
          "2018" : 0.03,
          "2017" : 0.05,
          "2016" : 0.1,
          "2015" : 0.1,
          "2012" : 0.1,
          "2010" : 0.1,
          "2008" : 0.1,
          "2005" : 0.1,
          "2000" : 0.0
        } ]
      }
    }, {
      "01011" : {
        "title" : "Baños de Ebro/Mañueta",
        "values" : [ {
          "2019" : 35.72,
          "2018" : 37.05,
          "2017" : 34.71,
          "2016" : 34.3,
          "2015" : 32.8,
          "2012" : 18.5,
          "2010" : 17.5,
          "2008" : 25.7,
          "2005" : 26.1,
          "2000" : 58.7
        } ]
      }
    }, {
      "20019" : {
        "title" : "Beasain",
        "values" : [ {
          "2019" : 0.16,
          "2018" : 0.12,
          "2017" : 0.2,
          "2016" : 0.2,
          "2015" : 0.2,
          "2012" : 0.1,
          "2010" : 0.1,
          "2008" : 0.1,
          "2005" : 0.3,
          "2000" : 0.3
        } ]
      }
    }, {
      "48092" : {
        "title" : "Bedia",
        "values" : [ {
          "2019" : 2.58,
          "2018" : 2.54,
          "2017" : 2.54,
          "2016" : 2.3,
          "2015" : 2.1,
          "2012" : 1.8,
          "2010" : 1.5,
          "2008" : 1.1,
          "2005" : 1.8,
          "2000" : 1.4
        } ]
      }
    }, {
      "20020" : {
        "title" : "Beizama",
        "values" : [ {
          "2019" : 23.78,
          "2018" : 18.5,
          "2017" : 20.53,
          "2016" : 19.2,
          "2015" : 16.5,
          "2012" : 16.7,
          "2010" : 18.9,
          "2008" : 19.2,
          "2005" : 30.0,
          "2000" : 27.7
        } ]
      }
    }, {
      "20021" : {
        "title" : "Belauntza",
        "values" : [ {
          "2019" : 1.15,
          "2018" : 0.91,
          "2017" : 1.21,
          "2016" : 1.3,
          "2015" : 1.4,
          "2012" : 1.6,
          "2010" : 1.7,
          "2008" : 1.5,
          "2005" : 1.9,
          "2000" : 0.9
        } ]
      }
    }, {
      "48016" : {
        "title" : "Berango",
        "values" : [ {
          "2019" : 0.47,
          "2018" : 0.53,
          "2017" : 0.69,
          "2016" : 0.7,
          "2015" : 0.9,
          "2012" : 1.1,
          "2010" : 1.1,
          "2008" : 0.9,
          "2005" : 0.9,
          "2000" : 0.8
        } ]
      }
    }, {
      "01014" : {
        "title" : "Berantevilla",
        "values" : [ {
          "2019" : 3.86,
          "2018" : 4.37,
          "2017" : 4.02,
          "2016" : 4.9,
          "2015" : 5.9,
          "2012" : 3.4,
          "2010" : 4.7,
          "2008" : 3.8,
          "2005" : 5.3,
          "2000" : 11.9
        } ]
      }
    }, {
      "20022" : {
        "title" : "Berastegi",
        "values" : [ {
          "2019" : 3.72,
          "2018" : 2.71,
          "2017" : 3.66,
          "2016" : 2.9,
          "2015" : 2.7,
          "2012" : 3.1,
          "2010" : 3.0,
          "2008" : 3.9,
          "2005" : 3.7,
          "2000" : 3.2
        } ]
      }
    }, {
      "20074" : {
        "title" : "Bergara",
        "values" : [ {
          "2019" : 0.8,
          "2018" : 0.58,
          "2017" : 0.89,
          "2016" : 0.8,
          "2015" : 0.8,
          "2012" : 0.6,
          "2010" : 0.5,
          "2008" : 0.5,
          "2005" : 0.7,
          "2000" : 0.7
        } ]
      }
    }, {
      "48017" : {
        "title" : "Bermeo",
        "values" : [ {
          "2019" : 32.53,
          "2018" : 30.82,
          "2017" : 33.17,
          "2016" : 14.2,
          "2015" : 12.9,
          "2012" : 30.1,
          "2010" : 21.8,
          "2008" : 14.4,
          "2005" : 24.4,
          "2000" : 22.1
        } ]
      }
    }, {
      "01016" : {
        "title" : "Bernedo",
        "values" : [ {
          "2019" : 6.96,
          "2018" : 7.45,
          "2017" : 7.51,
          "2016" : 7.6,
          "2015" : 7.8,
          "2012" : 6.1,
          "2010" : 5.5,
          "2008" : 3.9,
          "2005" : 7.3,
          "2000" : 14.1
        } ]
      }
    }, {
      "48018" : {
        "title" : "Berriatua",
        "values" : [ {
          "2019" : 1.38,
          "2018" : 1.19,
          "2017" : 1.21,
          "2016" : 1.4,
          "2015" : 1.5,
          "2012" : 1.7,
          "2010" : 1.5,
          "2008" : 1.3,
          "2005" : 1.7,
          "2000" : 2.2
        } ]
      }
    }, {
      "48019" : {
        "title" : "Berriz",
        "values" : [ {
          "2019" : 0.94,
          "2018" : 0.8,
          "2017" : 0.89,
          "2016" : 0.9,
          "2015" : 0.7,
          "2012" : 0.6,
          "2010" : 0.6,
          "2008" : 0.5,
          "2005" : 0.7,
          "2000" : 1.4
        } ]
      }
    }, {
      "20023" : {
        "title" : "Berrobi",
        "values" : [ {
          "2019" : 3.17,
          "2018" : 2.57,
          "2017" : 3.43,
          "2016" : 3.3,
          "2015" : 3.6,
          "2012" : 3.0,
          "2010" : 4.2,
          "2008" : 2.0,
          "2005" : 2.8,
          "2000" : 4.8
        } ]
      }
    }, {
      "20024" : {
        "title" : "Bidania-Goiatz",
        "values" : [ {
          "2019" : 6.48,
          "2018" : 5.75,
          "2017" : 6.24,
          "2016" : 6.3,
          "2015" : 6.7,
          "2012" : 5.8,
          "2010" : 6.6,
          "2008" : 7.8,
          "2005" : 7.9,
          "2000" : 9.5
        } ]
      }
    }, {
      "48020" : {
        "title" : "Bilbao",
        "values" : [ {
          "2019" : 0.06,
          "2018" : 0.06,
          "2017" : 0.09,
          "2016" : 0.0,
          "2015" : 0.0,
          "2012" : 0.1,
          "2010" : 0.0,
          "2008" : 0.0,
          "2005" : 0.0,
          "2000" : 0.0
        } ]
      }
    }, {
      "48021" : {
        "title" : "Busturia",
        "values" : [ {
          "2019" : 4.75,
          "2018" : 4.35,
          "2017" : 5.0,
          "2016" : 5.1,
          "2015" : 5.9,
          "2012" : 6.1,
          "2010" : 5.8,
          "2008" : 6.2,
          "2005" : 6.5,
          "2000" : 3.7
        } ]
      }
    }, {
      "01017" : {
        "title" : "Campezo/Kanpezu",
        "values" : [ {
          "2019" : 11.26,
          "2018" : 12.64,
          "2017" : 11.31,
          "2016" : 13.2,
          "2015" : 13.0,
          "2012" : 9.4,
          "2010" : 8.9,
          "2008" : 6.8,
          "2005" : 9.5,
          "2000" : 15.5
        } ]
      }
    }, {
      "20029" : {
        "title" : "Deba",
        "values" : [ {
          "2019" : 1.21,
          "2018" : 0.9,
          "2017" : 1.29,
          "2016" : 1.1,
          "2015" : 1.1,
          "2012" : 1.0,
          "2010" : 1.2,
          "2008" : 1.1,
          "2005" : 1.7,
          "2000" : 1.8
        } ]
      }
    }, {
      "48901" : {
        "title" : "Derio",
        "values" : [ {
          "2019" : 0.18,
          "2018" : 0.16,
          "2017" : 0.18,
          "2016" : 0.2,
          "2015" : 0.2,
          "2012" : 0.2,
          "2010" : 0.2,
          "2008" : 0.2,
          "2005" : 0.3,
          "2000" : 1.0
        } ]
      }
    }, {
      "48026" : {
        "title" : "Dima",
        "values" : [ {
          "2019" : 8.56,
          "2018" : 7.12,
          "2017" : 7.71,
          "2016" : 7.8,
          "2015" : 6.3,
          "2012" : 5.6,
          "2010" : 4.3,
          "2008" : 4.4,
          "2005" : 6.6,
          "2000" : 11.0
        } ]
      }
    }, {
      "20069" : {
        "title" : "Donostia / San Sebastián",
        "values" : [ {
          "2019" : 0.04,
          "2018" : 0.04,
          "2017" : 0.04,
          "2016" : 0.0,
          "2015" : 0.1,
          "2012" : 0.1,
          "2010" : 0.1,
          "2008" : 0.1,
          "2005" : 0.1,
          "2000" : 0.1
        } ]
      }
    }, {
      "48027" : {
        "title" : "Durango",
        "values" : [ {
          "2019" : 0.1,
          "2018" : 0.09,
          "2017" : 0.1,
          "2016" : 0.1,
          "2015" : 0.1,
          "2012" : 0.1,
          "2010" : 0.1,
          "2008" : 0.1,
          "2005" : 0.1,
          "2000" : 0.1
        } ]
      }
    }, {
      "48028" : {
        "title" : "Ea",
        "values" : [ {
          "2019" : 4.91,
          "2018" : 4.28,
          "2017" : 4.95,
          "2016" : 4.7,
          "2015" : 5.2,
          "2012" : 5.1,
          "2010" : 4.9,
          "2008" : 3.9,
          "2005" : 3.9,
          "2000" : 8.5
        } ]
      }
    }, {
      "20030" : {
        "title" : "Eibar",
        "values" : [ {
          "2019" : 0.22,
          "2018" : 0.17,
          "2017" : 0.21,
          "2016" : 0.2,
          "2015" : 0.1,
          "2012" : 0.1,
          "2010" : 0.1,
          "2008" : 0.1,
          "2005" : 0.1,
          "2000" : 0.1
        } ]
      }
    }, {
      "48031" : {
        "title" : "Elantxobe",
        "values" : [ {
          "2019" : 1.1,
          "2018" : 0.99,
          "2017" : 1.21,
          "2016" : 1.3,
          "2015" : 1.6,
          "2012" : 2.0,
          "2010" : 7.1,
          "2008" : 10.8,
          "2005" : 11.8,
          "2000" : 15.3
        } ]
      }
    }, {
      "01021" : {
        "title" : "Elburgo/Burgelu",
        "values" : [ {
          "2019" : 18.1,
          "2018" : 17.28,
          "2017" : 17.34,
          "2016" : 20.2,
          "2015" : 25.6,
          "2012" : 17.0,
          "2010" : 18.4,
          "2008" : 14.6,
          "2005" : 19.7,
          "2000" : 27.7
        } ]
      }
    }, {
      "01022" : {
        "title" : "Elciego",
        "values" : [ {
          "2019" : 12.51,
          "2018" : 14.12,
          "2017" : 12.62,
          "2016" : 13.8,
          "2015" : 13.3,
          "2012" : 6.0,
          "2010" : 5.9,
          "2008" : 12.4,
          "2005" : 12.4,
          "2000" : 27.8
        } ]
      }
    }, {
      "20031" : {
        "title" : "Elduain",
        "values" : [ {
          "2019" : 7.77,
          "2018" : 6.51,
          "2017" : 7.26,
          "2016" : 5.8,
          "2015" : 7.1,
          "2012" : 8.2,
          "2010" : 9.1,
          "2008" : 6.4,
          "2005" : 12.6,
          "2000" : 31.8
        } ]
      }
    }, {
      "20033" : {
        "title" : "Elgeta",
        "values" : [ {
          "2019" : 1.34,
          "2018" : 0.94,
          "2017" : 1.49,
          "2016" : 1.2,
          "2015" : 1.0,
          "2012" : 0.7,
          "2010" : 0.7,
          "2008" : 0.6,
          "2005" : 0.9,
          "2000" : 0.8
        } ]
      }
    }, {
      "20032" : {
        "title" : "Elgoibar",
        "values" : [ {
          "2019" : 0.45,
          "2018" : 0.33,
          "2017" : 0.42,
          "2016" : 0.3,
          "2015" : 0.3,
          "2012" : 0.2,
          "2010" : 0.3,
          "2008" : 0.3,
          "2005" : 0.4,
          "2000" : 0.6
        } ]
      }
    }, {
      "48032" : {
        "title" : "Elorrio",
        "values" : [ {
          "2019" : 0.84,
          "2018" : 0.73,
          "2017" : 0.74,
          "2016" : 0.8,
          "2015" : 0.5,
          "2012" : 0.5,
          "2010" : 0.4,
          "2008" : 0.3,
          "2005" : 0.5,
          "2000" : 0.8
        } ]
      }
    }, {
      "01023" : {
        "title" : "Elvillar/Bilar",
        "values" : [ {
          "2019" : 48.9,
          "2018" : 50.58,
          "2017" : 43.0,
          "2016" : 39.6,
          "2015" : 33.5,
          "2012" : 18.4,
          "2010" : 18.3,
          "2008" : 27.9,
          "2005" : 22.7,
          "2000" : 65.3
        } ]
      }
    }, {
      "48902" : {
        "title" : "Erandio",
        "values" : [ {
          "2019" : 0.11,
          "2018" : 0.1,
          "2017" : 0.14,
          "2016" : 0.1,
          "2015" : 0.1,
          "2012" : 0.1,
          "2010" : 0.1,
          "2008" : 0.1,
          "2005" : 0.1,
          "2000" : 0.3
        } ]
      }
    }, {
      "48033" : {
        "title" : "Ereño",
        "values" : [ {
          "2019" : 14.88,
          "2018" : 11.94,
          "2017" : 8.37,
          "2016" : 8.6,
          "2015" : 10.3,
          "2012" : 12.2,
          "2010" : 10.2,
          "2008" : 7.9,
          "2005" : 8.9,
          "2000" : 14.8
        } ]
      }
    }, {
      "48034" : {
        "title" : "Ermua",
        "values" : [ {
          "2019" : 0.06,
          "2018" : 0.05,
          "2017" : 0.05,
          "2016" : 0.1,
          "2015" : 0.1,
          "2012" : 0.1,
          "2010" : 0.0,
          "2008" : 0.0,
          "2005" : 0.1,
          "2000" : 0.1
        } ]
      }
    }, {
      "20067" : {
        "title" : "Errenteria",
        "values" : [ {
          "2019" : 0.15,
          "2018" : 0.12,
          "2017" : 0.16,
          "2016" : 0.1,
          "2015" : 0.1,
          "2012" : 0.1,
          "2010" : 0.1,
          "2008" : 0.2,
          "2005" : 0.3,
          "2000" : 0.4
        } ]
      }
    }, {
      "20066" : {
        "title" : "Errezil",
        "values" : [ {
          "2019" : 7.28,
          "2018" : 6.04,
          "2017" : 7.38,
          "2016" : 6.3,
          "2015" : 5.1,
          "2012" : 5.2,
          "2010" : 5.7,
          "2008" : 7.8,
          "2005" : 8.5,
          "2000" : 10.2
        } ]
      }
    }, {
      "01046" : {
        "title" : "Erriberagoitia/Ribera Alta",
        "values" : [ {
          "2019" : 26.91,
          "2018" : 25.82,
          "2017" : 23.01,
          "2016" : 25.1,
          "2015" : 22.5,
          "2012" : 25.3,
          "2010" : 23.3,
          "2008" : 18.9,
          "2005" : 26.6,
          "2000" : 35.7
        } ]
      }
    }, {
      "48079" : {
        "title" : "Errigoiti",
        "values" : [ {
          "2019" : 14.69,
          "2018" : 13.37,
          "2017" : 15.39,
          "2016" : 14.1,
          "2015" : 12.6,
          "2012" : 11.9,
          "2010" : 10.1,
          "2008" : 8.1,
          "2005" : 8.9,
          "2000" : 13.9
        } ]
      }
    }, {
      "20034" : {
        "title" : "Eskoriatza",
        "values" : [ {
          "2019" : 1.02,
          "2018" : 0.86,
          "2017" : 0.96,
          "2016" : 0.8,
          "2015" : 0.7,
          "2012" : 0.6,
          "2010" : 0.5,
          "2008" : 0.5,
          "2005" : 0.8,
          "2000" : 1.1
        } ]
      }
    }, {
      "48029" : {
        "title" : "Etxebarri",
        "values" : [ {
          "2019" : 0.02,
          "2018" : 0.02,
          "2017" : 0.03,
          "2016" : 0.0,
          "2015" : 0.0,
          "2012" : 0.1,
          "2010" : 0.0,
          "2008" : 0.0,
          "2005" : 0.1,
          "2000" : 0.1
        } ]
      }
    }, {
      "48030" : {
        "title" : "Etxebarria",
        "values" : [ {
          "2019" : 1.09,
          "2018" : 0.9,
          "2017" : 0.81,
          "2016" : 0.9,
          "2015" : 0.9,
          "2012" : 2.1,
          "2010" : 3.7,
          "2008" : 1.2,
          "2005" : 1.6,
          "2000" : 2.2
        } ]
      }
    }, {
      "20035" : {
        "title" : "Ezkio-Itsaso",
        "values" : [ {
          "2019" : 2.11,
          "2018" : 1.61,
          "2017" : 2.5,
          "2016" : 1.9,
          "2015" : 1.7,
          "2012" : 1.8,
          "2010" : 1.9,
          "2008" : 1.5,
          "2005" : 2.3,
          "2000" : 2.8
        } ]
      }
    }, {
      "48906" : {
        "title" : "Forua",
        "values" : [ {
          "2019" : 4.86,
          "2018" : 4.54,
          "2017" : 4.98,
          "2016" : 5.2,
          "2015" : 5.2,
          "2012" : 4.9,
          "2010" : 4.4,
          "2008" : 3.4,
          "2005" : 2.9,
          "2000" : 3.5
        } ]
      }
    }, {
      "48035" : {
        "title" : "Fruiz",
        "values" : [ {
          "2019" : 5.06,
          "2018" : 4.81,
          "2017" : 5.21,
          "2016" : 6.2,
          "2015" : 7.1,
          "2012" : 8.1,
          "2010" : 8.0,
          "2008" : 3.8,
          "2005" : 8.5,
          "2000" : 7.1
        } ]
      }
    }, {
      "20038" : {
        "title" : "Gabiria",
        "values" : [ {
          "2019" : 5.81,
          "2018" : 4.92,
          "2017" : 6.64,
          "2016" : 6.3,
          "2015" : 6.6,
          "2012" : 5.9,
          "2010" : 4.3,
          "2008" : 4.3,
          "2005" : 5.0,
          "2000" : 13.7
        } ]
      }
    }, {
      "20037" : {
        "title" : "Gaintza",
        "values" : [ {
          "2019" : 15.69,
          "2018" : 12.31,
          "2017" : 16.46,
          "2016" : 13.8,
          "2015" : 13.9,
          "2012" : 12.3,
          "2010" : 13.8,
          "2008" : 11.3,
          "2005" : 12.7,
          "2000" : 8.7
        } ]
      }
    }, {
      "48036" : {
        "title" : "Galdakao",
        "values" : [ {
          "2019" : 0.12,
          "2018" : 0.11,
          "2017" : 0.12,
          "2016" : 0.1,
          "2015" : 0.2,
          "2012" : 0.2,
          "2010" : 0.2,
          "2008" : 0.2,
          "2005" : 0.2,
          "2000" : 0.5
        } ]
      }
    }, {
      "48037" : {
        "title" : "Galdames",
        "values" : [ {
          "2019" : 7.77,
          "2018" : 7.44,
          "2017" : 8.34,
          "2016" : 8.8,
          "2015" : 6.9,
          "2012" : 5.6,
          "2010" : 5.3,
          "2008" : 4.9,
          "2005" : 5.8,
          "2000" : 15.9
        } ]
      }
    }, {
      "48038" : {
        "title" : "Gamiz-Fika",
        "values" : [ {
          "2019" : 11.37,
          "2018" : 11.42,
          "2017" : 12.98,
          "2016" : 14.4,
          "2015" : 18.8,
          "2012" : 16.8,
          "2010" : 17.2,
          "2008" : 18.8,
          "2005" : 15.0,
          "2000" : 29.2
        } ]
      }
    }, {
      "48039" : {
        "title" : "Garai",
        "values" : [ {
          "2019" : 6.41,
          "2018" : 6.07,
          "2017" : 6.41,
          "2016" : 6.9,
          "2015" : 6.0,
          "2012" : 5.4,
          "2010" : 4.4,
          "2008" : 5.2,
          "2005" : 8.3,
          "2000" : 14.5
        } ]
      }
    }, {
      "48040" : {
        "title" : "Gatika",
        "values" : [ {
          "2019" : 2.57,
          "2018" : 2.34,
          "2017" : 2.69,
          "2016" : 2.7,
          "2015" : 3.6,
          "2012" : 3.4,
          "2010" : 3.0,
          "2008" : 2.3,
          "2005" : 2.9,
          "2000" : 4.4
        } ]
      }
    }, {
      "48041" : {
        "title" : "Gautegiz Arteaga",
        "values" : [ {
          "2019" : 2.81,
          "2018" : 2.62,
          "2017" : 2.9,
          "2016" : 3.5,
          "2015" : 4.0,
          "2012" : 4.5,
          "2010" : 4.2,
          "2008" : 4.1,
          "2005" : 5.0,
          "2000" : 5.6
        } ]
      }
    }, {
      "20907" : {
        "title" : "Gaztelu",
        "values" : [ {
          "2019" : 19.86,
          "2018" : 15.57,
          "2017" : 18.18,
          "2016" : 16.4,
          "2015" : 13.8,
          "2012" : 8.9,
          "2010" : 14.8,
          "2008" : 16.2,
          "2005" : 26.7,
          "2000" : 32.9
        } ]
      }
    }, {
      "48046" : {
        "title" : "Gernika-Lumo",
        "values" : [ {
          "2019" : 0.33,
          "2018" : 0.28,
          "2017" : 0.26,
          "2016" : 0.2,
          "2015" : 0.2,
          "2012" : 0.2,
          "2010" : 0.2,
          "2008" : 0.1,
          "2005" : 0.2,
          "2000" : 0.4
        } ]
      }
    }, {
      "20039" : {
        "title" : "Getaria",
        "values" : [ {
          "2019" : 20.75,
          "2018" : 23.02,
          "2017" : 24.82,
          "2016" : 19.3,
          "2015" : 20.7,
          "2012" : 25.2,
          "2010" : 15.4,
          "2008" : 16.5,
          "2005" : 20.7,
          "2000" : 20.7
        } ]
      }
    }, {
      "48044" : {
        "title" : "Getxo",
        "values" : [ {
          "2019" : 0.04,
          "2018" : 0.05,
          "2017" : 0.07,
          "2016" : 0.1,
          "2015" : 0.1,
          "2012" : 0.1,
          "2010" : 0.1,
          "2008" : 0.1,
          "2005" : 0.1,
          "2000" : 0.1
        } ]
      }
    }, {
      "48047" : {
        "title" : "Gizaburuaga",
        "values" : [ {
          "2019" : 2.13,
          "2018" : 1.73,
          "2017" : 1.59,
          "2016" : 2.1,
          "2015" : 1.9,
          "2012" : 2.0,
          "2010" : 1.3,
          "2008" : 1.4,
          "2005" : 1.5,
          "2000" : 2.6
        } ]
      }
    }, {
      "48042" : {
        "title" : "Gordexola",
        "values" : [ {
          "2019" : 4.53,
          "2018" : 4.02,
          "2017" : 4.28,
          "2016" : 5.1,
          "2015" : 5.1,
          "2012" : 5.2,
          "2010" : 4.8,
          "2008" : 5.2,
          "2005" : 6.9,
          "2000" : 15.3
        } ]
      }
    }, {
      "48043" : {
        "title" : "Gorliz",
        "values" : [ {
          "2019" : 0.61,
          "2018" : 0.76,
          "2017" : 0.85,
          "2016" : 1.1,
          "2015" : 1.4,
          "2012" : 1.4,
          "2010" : 1.5,
          "2008" : 1.4,
          "2005" : 1.6,
          "2000" : 0.6
        } ]
      }
    }, {
      "48045" : {
        "title" : "Güeñes",
        "values" : [ {
          "2019" : 1.0,
          "2018" : 1.15,
          "2017" : 1.25,
          "2016" : 1.4,
          "2015" : 1.3,
          "2012" : 1.1,
          "2010" : 1.0,
          "2008" : 0.9,
          "2005" : 0.9,
          "2000" : 2.4
        } ]
      }
    }, {
      "01056" : {
        "title" : "Harana/Valle de Arana",
        "values" : [ {
          "2019" : 23.9,
          "2018" : 30.61,
          "2017" : 29.5,
          "2016" : 30.9,
          "2015" : 32.3,
          "2012" : 29.3,
          "2010" : 26.0,
          "2008" : 23.6,
          "2005" : 29.0,
          "2000" : 36.9
        } ]
      }
    }, {
      "20040" : {
        "title" : "Hernani",
        "values" : [ {
          "2019" : 0.27,
          "2018" : 0.26,
          "2017" : 0.33,
          "2016" : 0.4,
          "2015" : 0.5,
          "2012" : 0.5,
          "2010" : 0.4,
          "2008" : 0.4,
          "2005" : 0.5,
          "2000" : 0.4
        } ]
      }
    }, {
      "20041" : {
        "title" : "Hernialde",
        "values" : [ {
          "2019" : 5.49,
          "2018" : 5.4,
          "2017" : 6.98,
          "2016" : 5.8,
          "2015" : 7.3,
          "2012" : 5.5,
          "2010" : 6.0,
          "2008" : 8.0,
          "2005" : 10.9,
          "2000" : 9.7
        } ]
      }
    }, {
      "20036" : {
        "title" : "Hondarribia",
        "values" : [ {
          "2019" : 5.83,
          "2018" : 5.98,
          "2017" : 6.21,
          "2016" : 4.5,
          "2015" : 4.9,
          "2012" : 5.9,
          "2010" : 4.1,
          "2008" : 3.8,
          "2005" : 4.7,
          "2000" : 6.5
        } ]
      }
    }, {
      "20042" : {
        "title" : "Ibarra",
        "values" : [ {
          "2019" : 0.49,
          "2018" : 0.48,
          "2017" : 0.57,
          "2016" : 0.5,
          "2015" : 0.6,
          "2012" : 0.7,
          "2010" : 0.7,
          "2008" : 0.6,
          "2005" : 1.3,
          "2000" : 1.3
        } ]
      }
    }, {
      "48048" : {
        "title" : "Ibarrangelu",
        "values" : [ {
          "2019" : 3.93,
          "2018" : 3.48,
          "2017" : 4.32,
          "2016" : 4.2,
          "2015" : 4.4,
          "2012" : 4.4,
          "2010" : 4.4,
          "2008" : 4.9,
          "2005" : 8.8,
          "2000" : 9.0
        } ]
      }
    }, {
      "20043" : {
        "title" : "Idiazabal",
        "values" : [ {
          "2019" : 1.22,
          "2018" : 1.3,
          "2017" : 1.9,
          "2016" : 1.6,
          "2015" : 2.5,
          "2012" : 2.7,
          "2010" : 3.1,
          "2008" : 3.1,
          "2005" : 4.5,
          "2000" : 8.6
        } ]
      }
    }, {
      "48094" : {
        "title" : "Igorre",
        "values" : [ {
          "2019" : 0.61,
          "2018" : 0.54,
          "2017" : 0.51,
          "2016" : 0.5,
          "2015" : 0.4,
          "2012" : 0.3,
          "2010" : 0.2,
          "2008" : 0.2,
          "2005" : 0.3,
          "2000" : 0.4
        } ]
      }
    }, {
      "20044" : {
        "title" : "Ikaztegieta",
        "values" : [ {
          "2019" : 0.44,
          "2018" : 0.38,
          "2017" : 0.54,
          "2016" : 0.5,
          "2015" : 0.8,
          "2012" : 0.5,
          "2010" : 0.6,
          "2008" : 0.8,
          "2005" : 1.0,
          "2000" : 1.7
        } ]
      }
    }, {
      "20045" : {
        "title" : "Irun",
        "values" : [ {
          "2019" : 0.09,
          "2018" : 0.09,
          "2017" : 0.12,
          "2016" : 0.1,
          "2015" : 0.2,
          "2012" : 0.2,
          "2010" : 0.1,
          "2008" : 0.2,
          "2005" : 0.2,
          "2000" : 0.2
        } ]
      }
    }, {
      "20046" : {
        "title" : "Irura",
        "values" : [ {
          "2019" : 0.07,
          "2018" : 0.06,
          "2017" : 0.07,
          "2016" : 0.1,
          "2015" : 0.1,
          "2012" : 0.1,
          "2010" : 0.1,
          "2008" : 0.1,
          "2005" : 0.1,
          "2000" : 0.1
        } ]
      }
    }, {
      "01027" : {
        "title" : "Iruraiz-Gauna",
        "values" : [ {
          "2019" : 36.46,
          "2018" : 33.55,
          "2017" : 34.5,
          "2016" : 37.2,
          "2015" : 44.1,
          "2012" : 33.0,
          "2010" : 36.5,
          "2008" : 32.3,
          "2005" : 44.1,
          "2000" : 53.8
        } ]
      }
    }, {
      "01901" : {
        "title" : "Iruña Oka/Iruña de Oca",
        "values" : [ {
          "2019" : 0.87,
          "2018" : 0.9,
          "2017" : 0.88,
          "2016" : 1.0,
          "2015" : 1.2,
          "2012" : 1.1,
          "2010" : 1.1,
          "2008" : 0.9,
          "2005" : 1.1,
          "2000" : 1.4
        } ]
      }
    }, {
      "48049" : {
        "title" : "Ispaster",
        "values" : [ {
          "2019" : 12.58,
          "2018" : 11.46,
          "2017" : 8.78,
          "2016" : 9.4,
          "2015" : 8.7,
          "2012" : 7.8,
          "2010" : 8.2,
          "2008" : 6.3,
          "2005" : 8.1,
          "2000" : 10.5
        } ]
      }
    }, {
      "20047" : {
        "title" : "Itsasondo",
        "values" : [ {
          "2019" : 1.8,
          "2018" : 1.64,
          "2017" : 1.71,
          "2016" : 1.4,
          "2015" : 1.2,
          "2012" : 0.8,
          "2010" : 0.9,
          "2008" : 1.0,
          "2005" : 1.4,
          "2000" : 1.1
        } ]
      }
    }, {
      "48910" : {
        "title" : "Iurreta",
        "values" : [ {
          "2019" : 0.21,
          "2018" : 0.17,
          "2017" : 0.19,
          "2016" : 0.2,
          "2015" : 0.2,
          "2012" : 0.1,
          "2010" : 0.1,
          "2008" : 0.1,
          "2005" : 0.1,
          "2000" : 0.4
        } ]
      }
    }, {
      "48050" : {
        "title" : "Izurtza",
        "values" : [ {
          "2019" : 0.8,
          "2018" : 0.62,
          "2017" : 0.58,
          "2016" : 0.6,
          "2015" : 0.4,
          "2012" : 0.4,
          "2010" : 0.3,
          "2008" : 0.3,
          "2005" : 0.3,
          "2000" : 0.5
        } ]
      }
    }, {
      "48022" : {
        "title" : "Karrantza Harana/Valle de Carranza",
        "values" : [ {
          "2019" : 14.99,
          "2018" : 15.66,
          "2017" : 19.48,
          "2016" : 18.6,
          "2015" : 17.0,
          "2012" : 17.0,
          "2010" : 12.8,
          "2008" : 12.0,
          "2005" : 13.4,
          "2000" : 23.0
        } ]
      }
    }, {
      "48907" : {
        "title" : "Kortezubi",
        "values" : [ {
          "2019" : 19.06,
          "2018" : 17.46,
          "2017" : 21.34,
          "2016" : 23.4,
          "2015" : 29.7,
          "2012" : 22.3,
          "2010" : 24.9,
          "2008" : 26.3,
          "2005" : 30.9,
          "2000" : 22.2
        } ]
      }
    }, {
      "01019" : {
        "title" : "Kripan",
        "values" : [ {
          "2019" : 60.22,
          "2018" : 63.78,
          "2017" : 59.89,
          "2016" : 60.7,
          "2015" : 59.0,
          "2012" : 38.4,
          "2010" : 37.4,
          "2008" : 44.7,
          "2005" : 50.7,
          "2000" : 72.2
        } ]
      }
    }, {
      "01020" : {
        "title" : "Kuartango",
        "values" : [ {
          "2019" : 35.38,
          "2018" : 37.27,
          "2017" : 32.55,
          "2016" : 32.4,
          "2015" : 29.1,
          "2012" : 31.5,
          "2010" : 31.2,
          "2008" : 27.6,
          "2005" : 33.0,
          "2000" : 38.7
        } ]
      }
    }, {
      "01028" : {
        "title" : "Labastida/Bastida",
        "values" : [ {
          "2019" : 8.17,
          "2018" : 9.77,
          "2017" : 8.62,
          "2016" : 8.9,
          "2015" : 10.8,
          "2012" : 5.1,
          "2010" : 5.1,
          "2008" : 8.9,
          "2005" : 15.1,
          "2000" : 30.8
        } ]
      }
    }, {
      "01030" : {
        "title" : "Lagrán",
        "values" : [ {
          "2019" : 18.89,
          "2018" : 22.0,
          "2017" : 17.93,
          "2016" : 21.5,
          "2015" : 24.0,
          "2012" : 19.5,
          "2010" : 16.7,
          "2008" : 10.9,
          "2005" : 24.6,
          "2000" : 25.2
        } ]
      }
    }, {
      "01031" : {
        "title" : "Laguardia",
        "values" : [ {
          "2019" : 9.02,
          "2018" : 11.18,
          "2017" : 9.51,
          "2016" : 10.1,
          "2015" : 9.0,
          "2012" : 5.3,
          "2010" : 5.6,
          "2008" : 9.8,
          "2005" : 15.7,
          "2000" : 33.2
        } ]
      }
    }, {
      "01032" : {
        "title" : "Lanciego/Lantziego",
        "values" : [ {
          "2019" : 16.29,
          "2018" : 18.94,
          "2017" : 17.37,
          "2016" : 17.2,
          "2015" : 17.6,
          "2012" : 8.6,
          "2010" : 8.8,
          "2008" : 17.0,
          "2005" : 25.4,
          "2000" : 54.8
        } ]
      }
    }, {
      "48051" : {
        "title" : "Lanestosa",
        "values" : [ {
          "2019" : 5.61,
          "2018" : 5.71,
          "2017" : 5.44,
          "2016" : 5.0,
          "2015" : 4.4,
          "2012" : 4.1,
          "2010" : 2.0,
          "2008" : 5.1,
          "2005" : 7.7,
          "2000" : 8.1
        } ]
      }
    }, {
      "01902" : {
        "title" : "Lantarón",
        "values" : [ {
          "2019" : 3.08,
          "2018" : 2.99,
          "2017" : 3.35,
          "2016" : 3.8,
          "2015" : 4.5,
          "2012" : 4.6,
          "2010" : 4.5,
          "2008" : 3.0,
          "2005" : 4.6,
          "2000" : 7.2
        } ]
      }
    }, {
      "01033" : {
        "title" : "Lapuebla de Labarca",
        "values" : [ {
          "2019" : 5.6,
          "2018" : 4.76,
          "2017" : 3.68,
          "2016" : 3.0,
          "2015" : 2.4,
          "2012" : 1.2,
          "2010" : 1.2,
          "2008" : 2.2,
          "2005" : 2.7,
          "2000" : 8.9
        } ]
      }
    }, {
      "48052" : {
        "title" : "Larrabetzu",
        "values" : [ {
          "2019" : 1.17,
          "2018" : 1.13,
          "2017" : 1.43,
          "2016" : 2.0,
          "2015" : 2.6,
          "2012" : 2.5,
          "2010" : 3.4,
          "2008" : 4.1,
          "2005" : 3.1,
          "2000" : 7.5
        } ]
      }
    }, {
      "20048" : {
        "title" : "Larraul",
        "values" : [ {
          "2019" : 4.28,
          "2018" : 4.31,
          "2017" : 4.52,
          "2016" : 4.8,
          "2015" : 7.5,
          "2012" : 13.5,
          "2010" : 17.2,
          "2008" : 31.1,
          "2005" : 22.1,
          "2000" : 33.4
        } ]
      }
    }, {
      "20902" : {
        "title" : "Lasarte-Oria",
        "values" : [ {
          "2019" : 0.07,
          "2018" : 0.06,
          "2017" : 0.06,
          "2016" : 0.1,
          "2015" : 0.1,
          "2012" : 0.1,
          "2010" : 0.1,
          "2008" : 0.2,
          "2005" : 0.3,
          "2000" : 0.4
        } ]
      }
    }, {
      "01036" : {
        "title" : "Laudio/Llodio",
        "values" : [ {
          "2019" : 0.23,
          "2018" : 0.29,
          "2017" : 0.35,
          "2016" : 0.3,
          "2015" : 0.3,
          "2012" : 0.3,
          "2010" : 0.4,
          "2008" : 0.2,
          "2005" : 0.4,
          "2000" : 0.3
        } ]
      }
    }, {
      "48053" : {
        "title" : "Laukiz",
        "values" : [ {
          "2019" : 3.24,
          "2018" : 3.84,
          "2017" : 4.04,
          "2016" : 4.2,
          "2015" : 4.4,
          "2012" : 3.0,
          "2010" : 2.5,
          "2008" : 2.8,
          "2005" : 4.0,
          "2000" : 6.6
        } ]
      }
    }, {
      "20049" : {
        "title" : "Lazkao",
        "values" : [ {
          "2019" : 0.73,
          "2018" : 0.59,
          "2017" : 0.85,
          "2016" : 0.8,
          "2015" : 0.8,
          "2012" : 0.8,
          "2010" : 0.9,
          "2008" : 0.6,
          "2005" : 0.9,
          "2000" : 0.7
        } ]
      }
    }, {
      "20050" : {
        "title" : "Leaburu",
        "values" : [ {
          "2019" : 2.11,
          "2018" : 1.72,
          "2017" : 2.11,
          "2016" : 1.8,
          "2015" : 1.9,
          "2012" : 2.3,
          "2010" : 2.7,
          "2008" : 2.9,
          "2005" : 4.8,
          "2000" : 3.2
        } ]
      }
    }, {
      "20051" : {
        "title" : "Legazpi",
        "values" : [ {
          "2019" : 0.47,
          "2018" : 0.33,
          "2017" : 0.46,
          "2016" : 0.4,
          "2015" : 0.3,
          "2012" : 0.3,
          "2010" : 0.3,
          "2008" : 0.2,
          "2005" : 0.3,
          "2000" : 0.4
        } ]
      }
    }, {
      "20052" : {
        "title" : "Legorreta",
        "values" : [ {
          "2019" : 1.2,
          "2018" : 1.22,
          "2017" : 1.54,
          "2016" : 1.6,
          "2015" : 2.3,
          "2012" : 2.0,
          "2010" : 1.4,
          "2008" : 1.7,
          "2005" : 1.6,
          "2000" : 0.7
        } ]
      }
    }, {
      "01058" : {
        "title" : "Legutio",
        "values" : [ {
          "2019" : 0.42,
          "2018" : 0.6,
          "2017" : 0.64,
          "2016" : 0.9,
          "2015" : 1.2,
          "2012" : 1.0,
          "2010" : 0.9,
          "2008" : 0.6,
          "2005" : 0.8,
          "2000" : 0.9
        } ]
      }
    }, {
      "20068" : {
        "title" : "Leintz-Gatzaga",
        "values" : [ {
          "2019" : 6.72,
          "2018" : 4.97,
          "2017" : 7.26,
          "2016" : 6.3,
          "2015" : 5.8,
          "2012" : 4.7,
          "2010" : 4.3,
          "2008" : 4.2,
          "2005" : 5.7,
          "2000" : 4.7
        } ]
      }
    }, {
      "48054" : {
        "title" : "Leioa",
        "values" : [ {
          "2019" : 0.02,
          "2018" : 0.02,
          "2017" : 0.02,
          "2016" : 0.0,
          "2015" : 0.0,
          "2012" : 0.0,
          "2010" : 0.0,
          "2008" : 0.0,
          "2005" : 0.0,
          "2000" : 0.1
        } ]
      }
    }, {
      "48057" : {
        "title" : "Lekeitio",
        "values" : [ {
          "2019" : 3.06,
          "2018" : 3.48,
          "2017" : 3.49,
          "2016" : 2.8,
          "2015" : 2.0,
          "2012" : 2.0,
          "2010" : 1.5,
          "2008" : 1.1,
          "2005" : 2.7,
          "2000" : 2.8
        } ]
      }
    }, {
      "48055" : {
        "title" : "Lemoa",
        "values" : [ {
          "2019" : 0.61,
          "2018" : 0.54,
          "2017" : 0.53,
          "2016" : 0.6,
          "2015" : 0.5,
          "2012" : 0.4,
          "2010" : 0.3,
          "2008" : 0.2,
          "2005" : 0.3,
          "2000" : 0.7
        } ]
      }
    }, {
      "48056" : {
        "title" : "Lemoiz",
        "values" : [ {
          "2019" : 9.86,
          "2018" : 6.43,
          "2017" : 7.62,
          "2016" : 6.1,
          "2015" : 5.8,
          "2012" : 6.8,
          "2010" : 3.6,
          "2008" : 3.2,
          "2005" : 5.3,
          "2000" : 7.6
        } ]
      }
    }, {
      "01034" : {
        "title" : "Leza",
        "values" : [ {
          "2019" : 44.35,
          "2018" : 48.58,
          "2017" : 28.06,
          "2016" : 30.9,
          "2015" : 28.6,
          "2012" : 15.3,
          "2010" : 14.3,
          "2008" : 23.6,
          "2005" : 15.5,
          "2000" : 43.0
        } ]
      }
    }, {
      "48081" : {
        "title" : "Lezama",
        "values" : [ {
          "2019" : 1.05,
          "2018" : 1.19,
          "2017" : 1.19,
          "2016" : 1.1,
          "2015" : 1.1,
          "2012" : 1.0,
          "2010" : 1.1,
          "2008" : 1.2,
          "2005" : 1.7,
          "2000" : 4.6
        } ]
      }
    }, {
      "20053" : {
        "title" : "Lezo",
        "values" : [ {
          "2019" : 0.15,
          "2018" : 0.13,
          "2017" : 0.16,
          "2016" : 0.1,
          "2015" : 0.2,
          "2012" : 0.1,
          "2010" : 0.2,
          "2008" : 0.2,
          "2005" : 0.2,
          "2000" : 0.3
        } ]
      }
    }, {
      "20054" : {
        "title" : "Lizartza",
        "values" : [ {
          "2019" : 1.56,
          "2018" : 1.33,
          "2017" : 1.82,
          "2016" : 1.6,
          "2015" : 1.6,
          "2012" : 1.5,
          "2010" : 1.2,
          "2008" : 1.4,
          "2005" : 2.5,
          "2000" : 2.7
        } ]
      }
    }, {
      "48903" : {
        "title" : "Loiu",
        "values" : [ {
          "2019" : 0.16,
          "2018" : 0.14,
          "2017" : 0.17,
          "2016" : 0.2,
          "2015" : 0.2,
          "2012" : 0.2,
          "2010" : 0.2,
          "2008" : 0.3,
          "2005" : 0.3,
          "2000" : 0.8
        } ]
      }
    }, {
      "48058" : {
        "title" : "Mallabia",
        "values" : [ {
          "2019" : 0.82,
          "2018" : 0.76,
          "2017" : 0.91,
          "2016" : 1.1,
          "2015" : 1.0,
          "2012" : 0.9,
          "2010" : 0.8,
          "2008" : 0.6,
          "2005" : 0.8,
          "2000" : 1.9
        } ]
      }
    }, {
      "48060" : {
        "title" : "Markina-Xemein",
        "values" : [ {
          "2019" : 2.75,
          "2018" : 2.34,
          "2017" : 2.4,
          "2016" : 2.5,
          "2015" : 2.2,
          "2012" : 1.7,
          "2010" : 1.3,
          "2008" : 1.5,
          "2005" : 2.3,
          "2000" : 5.3
        } ]
      }
    }, {
      "48061" : {
        "title" : "Maruri-Jatabe",
        "values" : [ {
          "2019" : 6.67,
          "2018" : 5.69,
          "2017" : 6.38,
          "2016" : 7.4,
          "2015" : 5.2,
          "2012" : 8.1,
          "2010" : 7.8,
          "2008" : 3.6,
          "2005" : 8.7,
          "2000" : 10.6
        } ]
      }
    }, {
      "48059" : {
        "title" : "Mañaria",
        "values" : [ {
          "2019" : 2.59,
          "2018" : 2.42,
          "2017" : 2.92,
          "2016" : 2.7,
          "2015" : 1.7,
          "2012" : 1.4,
          "2010" : 0.7,
          "2008" : 0.5,
          "2005" : 0.7,
          "2000" : 3.5
        } ]
      }
    }, {
      "20901" : {
        "title" : "Mendaro",
        "values" : [ {
          "2019" : 0.7,
          "2018" : 0.53,
          "2017" : 0.68,
          "2016" : 0.6,
          "2015" : 0.5,
          "2012" : 0.4,
          "2010" : 0.4,
          "2008" : 0.4,
          "2005" : 0.6,
          "2000" : 0.7
        } ]
      }
    }, {
      "48062" : {
        "title" : "Mendata",
        "values" : [ {
          "2019" : 31.05,
          "2018" : 28.61,
          "2017" : 31.47,
          "2016" : 28.7,
          "2015" : 24.4,
          "2012" : 19.1,
          "2010" : 15.7,
          "2008" : 16.4,
          "2005" : 24.4,
          "2000" : 26.5
        } ]
      }
    }, {
      "48063" : {
        "title" : "Mendexa",
        "values" : [ {
          "2019" : 8.72,
          "2018" : 6.63,
          "2017" : 7.77,
          "2016" : 7.8,
          "2015" : 9.3,
          "2012" : 10.7,
          "2010" : 9.2,
          "2008" : 9.1,
          "2005" : 10.6,
          "2000" : 7.7
        } ]
      }
    }, {
      "48064" : {
        "title" : "Meñaka",
        "values" : [ {
          "2019" : 6.71,
          "2018" : 6.86,
          "2017" : 7.21,
          "2016" : 7.2,
          "2015" : 5.3,
          "2012" : 5.6,
          "2010" : 5.2,
          "2008" : 4.9,
          "2005" : 7.3,
          "2000" : 16.6
        } ]
      }
    }, {
      "01039" : {
        "title" : "Moreda de Álava / Moreda Araba",
        "values" : [ {
          "2019" : 34.75,
          "2018" : 39.38,
          "2017" : 36.18,
          "2016" : 38.1,
          "2015" : 30.8,
          "2012" : 21.6,
          "2010" : 23.3,
          "2008" : 33.2,
          "2005" : 45.8,
          "2000" : 73.6
        } ]
      }
    }, {
      "48066" : {
        "title" : "Morga",
        "values" : [ {
          "2019" : 13.47,
          "2018" : 15.08,
          "2017" : 18.53,
          "2016" : 19.4,
          "2015" : 17.3,
          "2012" : 13.6,
          "2010" : 14.4,
          "2008" : 14.9,
          "2005" : 15.1,
          "2000" : 22.2
        } ]
      }
    }, {
      "48068" : {
        "title" : "Mundaka",
        "values" : [ {
          "2019" : 0.55,
          "2018" : 0.7,
          "2017" : 0.65,
          "2016" : 1.3,
          "2015" : 1.2,
          "2012" : 1.9,
          "2010" : 1.2,
          "2008" : 0.9,
          "2005" : 2.1,
          "2000" : 1.6
        } ]
      }
    }, {
      "48069" : {
        "title" : "Mungia",
        "values" : [ {
          "2019" : 0.44,
          "2018" : 0.41,
          "2017" : 0.49,
          "2016" : 0.6,
          "2015" : 0.7,
          "2012" : 0.6,
          "2010" : 0.6,
          "2008" : 0.6,
          "2005" : 0.7,
          "2000" : 1.8
        } ]
      }
    }, {
      "48007" : {
        "title" : "Munitibar-Arbatzegi Gerrikaitz-",
        "values" : [ {
          "2019" : 13.62,
          "2018" : 11.13,
          "2017" : 11.49,
          "2016" : 12.2,
          "2015" : 10.6,
          "2012" : 9.6,
          "2010" : 10.3,
          "2008" : 8.2,
          "2005" : 11.9,
          "2000" : 18.1
        } ]
      }
    }, {
      "48908" : {
        "title" : "Murueta",
        "values" : [ {
          "2019" : 4.36,
          "2018" : 4.56,
          "2017" : 5.7,
          "2016" : 5.3,
          "2015" : 4.3,
          "2012" : 3.4,
          "2010" : 2.4,
          "2008" : 2.1,
          "2005" : 2.7,
          "2000" : 2.0
        } ]
      }
    }, {
      "48071" : {
        "title" : "Muskiz",
        "values" : [ {
          "2019" : 0.22,
          "2018" : 0.19,
          "2017" : 0.2,
          "2016" : 0.2,
          "2015" : 0.2,
          "2012" : 0.6,
          "2010" : 0.3,
          "2008" : 0.3,
          "2005" : 0.1,
          "2000" : 0.2
        } ]
      }
    }, {
      "20057" : {
        "title" : "Mutiloa",
        "values" : [ {
          "2019" : 7.66,
          "2018" : 7.05,
          "2017" : 13.71,
          "2016" : 11.6,
          "2015" : 10.0,
          "2012" : 8.9,
          "2010" : 5.5,
          "2008" : 8.3,
          "2005" : 9.8,
          "2000" : 9.1
        } ]
      }
    }, {
      "20056" : {
        "title" : "Mutriku",
        "values" : [ {
          "2019" : 2.51,
          "2018" : 2.45,
          "2017" : 2.51,
          "2016" : 2.3,
          "2015" : 2.1,
          "2012" : 2.6,
          "2010" : 2.8,
          "2008" : 2.0,
          "2005" : 3.1,
          "2000" : 4.2
        } ]
      }
    }, {
      "48067" : {
        "title" : "Muxika",
        "values" : [ {
          "2019" : 8.66,
          "2018" : 7.42,
          "2017" : 8.04,
          "2016" : 8.4,
          "2015" : 8.1,
          "2012" : 6.6,
          "2010" : 4.6,
          "2008" : 4.0,
          "2005" : 5.1,
          "2000" : 5.4
        } ]
      }
    }, {
      "48909" : {
        "title" : "Nabarniz",
        "values" : [ {
          "2019" : 13.72,
          "2018" : 12.45,
          "2017" : 12.73,
          "2016" : 13.0,
          "2015" : 11.5,
          "2012" : 8.0,
          "2010" : 6.3,
          "2008" : 7.9,
          "2005" : 12.7,
          "2000" : 14.6
        } ]
      }
    }, {
      "01041" : {
        "title" : "Navaridas",
        "values" : [ {
          "2019" : 39.49,
          "2018" : 43.17,
          "2017" : 38.51,
          "2016" : 40.8,
          "2015" : 36.5,
          "2012" : 18.6,
          "2010" : 17.1,
          "2008" : 28.3,
          "2005" : 20.9,
          "2000" : 63.8
        } ]
      }
    }, {
      "20063" : {
        "title" : "Oiartzun",
        "values" : [ {
          "2019" : 0.31,
          "2018" : 0.27,
          "2017" : 0.37,
          "2016" : 0.4,
          "2015" : 0.5,
          "2012" : 0.5,
          "2010" : 0.5,
          "2008" : 0.5,
          "2005" : 0.6,
          "2000" : 0.7
        } ]
      }
    }, {
      "01042" : {
        "title" : "Okondo",
        "values" : [ {
          "2019" : 4.12,
          "2018" : 5.16,
          "2017" : 5.7,
          "2016" : 5.5,
          "2015" : 4.8,
          "2012" : 4.2,
          "2010" : 5.5,
          "2008" : 2.6,
          "2005" : 4.6,
          "2000" : 6.4
        } ]
      }
    }, {
      "20058" : {
        "title" : "Olaberria",
        "values" : [ {
          "2019" : 0.24,
          "2018" : 0.23,
          "2017" : 0.28,
          "2016" : 0.2,
          "2015" : 0.2,
          "2012" : 0.2,
          "2010" : 0.3,
          "2008" : 0.2,
          "2005" : 0.2,
          "2000" : 0.4
        } ]
      }
    }, {
      "48073" : {
        "title" : "Ondarroa",
        "values" : [ {
          "2019" : 17.07,
          "2018" : 14.76,
          "2017" : 17.37,
          "2016" : 17.9,
          "2015" : 17.6,
          "2012" : 12.3,
          "2010" : 17.3,
          "2008" : 14.7,
          "2005" : 16.1,
          "2000" : 17.2
        } ]
      }
    }, {
      "20076" : {
        "title" : "Ordizia",
        "values" : [ {
          "2019" : 0.16,
          "2018" : 0.14,
          "2017" : 0.16,
          "2016" : 0.1,
          "2015" : 0.1,
          "2012" : 0.1,
          "2010" : 0.1,
          "2008" : 0.1,
          "2005" : 0.1,
          "2000" : 0.1
        } ]
      }
    }, {
      "20905" : {
        "title" : "Orendain",
        "values" : [ {
          "2019" : 15.07,
          "2018" : 14.18,
          "2017" : 17.98,
          "2016" : 18.6,
          "2015" : 16.8,
          "2012" : 25.4,
          "2010" : 28.7,
          "2008" : 28.2,
          "2005" : 37.1,
          "2000" : 24.9
        } ]
      }
    }, {
      "20060" : {
        "title" : "Orexa",
        "values" : [ {
          "2019" : 10.48,
          "2018" : 14.24,
          "2017" : 16.64,
          "2016" : 14.0,
          "2015" : 11.2,
          "2012" : 9.6,
          "2010" : 8.9,
          "2008" : 9.5,
          "2005" : 12.9,
          "2000" : 25.3
        } ]
      }
    }, {
      "20061" : {
        "title" : "Orio",
        "values" : [ {
          "2019" : 6.32,
          "2018" : 7.68,
          "2017" : 7.81,
          "2016" : 5.8,
          "2015" : 5.2,
          "2012" : 7.1,
          "2010" : 4.9,
          "2008" : 6.2,
          "2005" : 6.7,
          "2000" : 8.4
        } ]
      }
    }, {
      "20062" : {
        "title" : "Ormaiztegi",
        "values" : [ {
          "2019" : 0.33,
          "2018" : 0.24,
          "2017" : 0.34,
          "2016" : 0.3,
          "2015" : 0.3,
          "2012" : 0.4,
          "2010" : 0.3,
          "2008" : 0.3,
          "2005" : 0.3,
          "2000" : 0.1
        } ]
      }
    }, {
      "48075" : {
        "title" : "Orozko",
        "values" : [ {
          "2019" : 1.81,
          "2018" : 1.62,
          "2017" : 2.17,
          "2016" : 2.5,
          "2015" : 2.6,
          "2012" : 2.6,
          "2010" : 1.5,
          "2008" : 2.4,
          "2005" : 2.7,
          "2000" : 5.7
        } ]
      }
    }, {
      "48083" : {
        "title" : "Ortuella",
        "values" : [ {
          "2019" : 0.07,
          "2018" : 0.06,
          "2017" : 0.07,
          "2016" : 0.1,
          "2015" : 0.1,
          "2012" : 0.1,
          "2010" : 0.1,
          "2008" : 0.1,
          "2005" : 0.1,
          "2000" : 0.2
        } ]
      }
    }, {
      "48072" : {
        "title" : "Otxandio",
        "values" : [ {
          "2019" : 0.75,
          "2018" : 0.74,
          "2017" : 0.83,
          "2016" : 0.9,
          "2015" : 1.0,
          "2012" : 0.8,
          "2010" : 0.6,
          "2008" : 0.6,
          "2005" : 0.7,
          "2000" : 1.1
        } ]
      }
    }, {
      "01043" : {
        "title" : "Oyón-Oion",
        "values" : [ {
          "2019" : 8.58,
          "2018" : 9.02,
          "2017" : 7.0,
          "2016" : 6.0,
          "2015" : 4.9,
          "2012" : 2.4,
          "2010" : 2.3,
          "2008" : 3.7,
          "2005" : 4.0,
          "2000" : 10.2
        } ]
      }
    }, {
      "20059" : {
        "title" : "Oñati",
        "values" : [ {
          "2019" : 0.67,
          "2018" : 0.56,
          "2017" : 0.84,
          "2016" : 0.7,
          "2015" : 0.7,
          "2012" : 0.7,
          "2010" : 0.6,
          "2008" : 0.5,
          "2005" : 0.6,
          "2000" : 0.8
        } ]
      }
    }, {
      "20064" : {
        "title" : "Pasaia",
        "values" : [ {
          "2019" : 3.84,
          "2018" : 2.57,
          "2017" : 2.08,
          "2016" : 2.4,
          "2015" : 2.4,
          "2012" : 3.6,
          "2010" : 2.4,
          "2008" : 1.8,
          "2005" : 4.4,
          "2000" : 3.3
        } ]
      }
    }, {
      "01044" : {
        "title" : "Peñacerrada-Urizaharra",
        "values" : [ {
          "2019" : 33.21,
          "2018" : 31.68,
          "2017" : 30.79,
          "2016" : 32.1,
          "2015" : 29.3,
          "2012" : 22.4,
          "2010" : 24.6,
          "2008" : 20.7,
          "2005" : 28.1,
          "2000" : 41.1
        } ]
      }
    }, {
      "48077" : {
        "title" : "Plentzia",
        "values" : [ {
          "2019" : 1.27,
          "2018" : 1.43,
          "2017" : 1.46,
          "2016" : 2.1,
          "2015" : 2.6,
          "2012" : 1.7,
          "2010" : 2.1,
          "2008" : 1.9,
          "2005" : 2.0,
          "2000" : 1.0
        } ]
      }
    }, {
      "48078" : {
        "title" : "Portugalete",
        "values" : [ {
          "2019" : 0.0,
          "2018" : 0.0,
          "2017" : 0.0,
          "2016" : 0.0,
          "2015" : 0.0,
          "2012" : 0.0,
          "2010" : 0.0,
          "2008" : 0.0,
          "2005" : 0.0,
          "2000" : 0.0
        } ]
      }
    }, {
      "01047" : {
        "title" : "Ribera Baja/Erribera Beitia",
        "values" : [ {
          "2019" : 1.62,
          "2018" : 1.85,
          "2017" : 1.71,
          "2016" : 1.5,
          "2015" : 1.3,
          "2012" : 1.4,
          "2010" : 1.5,
          "2008" : 1.3,
          "2005" : 2.2,
          "2000" : 3.9
        } ]
      }
    }, {
      "01051" : {
        "title" : "Salvatierra/Agurain",
        "values" : [ {
          "2019" : 1.54,
          "2018" : 1.58,
          "2017" : 1.74,
          "2016" : 2.2,
          "2015" : 2.7,
          "2012" : 2.4,
          "2010" : 2.3,
          "2008" : 1.1,
          "2005" : 1.4,
          "2000" : 2.2
        } ]
      }
    }, {
      "01052" : {
        "title" : "Samaniego",
        "values" : [ {
          "2019" : 19.63,
          "2018" : 23.33,
          "2017" : 21.07,
          "2016" : 23.0,
          "2015" : 19.5,
          "2012" : 8.7,
          "2010" : 8.3,
          "2008" : 15.5,
          "2005" : 11.8,
          "2000" : 43.3
        } ]
      }
    }, {
      "01053" : {
        "title" : "San Millán/Donemiliaga",
        "values" : [ {
          "2019" : 20.36,
          "2018" : 23.92,
          "2017" : 22.8,
          "2016" : 23.9,
          "2015" : 23.0,
          "2012" : 20.1,
          "2010" : 21.6,
          "2008" : 16.0,
          "2005" : 21.2,
          "2000" : 32.8
        } ]
      }
    }, {
      "48082" : {
        "title" : "Santurtzi",
        "values" : [ {
          "2019" : 0.27,
          "2018" : 0.22,
          "2017" : 0.16,
          "2016" : 0.2,
          "2015" : 0.2,
          "2012" : 0.2,
          "2010" : 0.2,
          "2008" : 0.2,
          "2005" : 0.2,
          "2000" : 0.2
        } ]
      }
    }, {
      "20070" : {
        "title" : "Segura",
        "values" : [ {
          "2019" : 2.88,
          "2018" : 2.38,
          "2017" : 2.85,
          "2016" : 2.4,
          "2015" : 2.7,
          "2012" : 2.5,
          "2010" : 2.4,
          "2008" : 1.9,
          "2005" : 2.8,
          "2000" : 3.1
        } ]
      }
    }, {
      "48084" : {
        "title" : "Sestao",
        "values" : [ {
          "2019" : 0.0,
          "2018" : 0.0,
          "2017" : 0.0,
          "2016" : 0.0,
          "2015" : 0.0,
          "2012" : 0.0,
          "2010" : 0.0,
          "2008" : 0.0,
          "2005" : 0.0,
          "2000" : 0.0
        } ]
      }
    }, {
      "48904" : {
        "title" : "Sondika",
        "values" : [ {
          "2019" : 0.08,
          "2018" : 0.08,
          "2017" : 0.09,
          "2016" : 0.1,
          "2015" : 0.1,
          "2012" : 0.1,
          "2010" : 0.1,
          "2008" : 0.1,
          "2005" : 0.1,
          "2000" : 0.1
        } ]
      }
    }, {
      "48085" : {
        "title" : "Sopela",
        "values" : [ {
          "2019" : 0.28,
          "2018" : 0.34,
          "2017" : 0.46,
          "2016" : 0.5,
          "2015" : 0.8,
          "2012" : 0.8,
          "2010" : 0.9,
          "2008" : 0.9,
          "2005" : 0.8,
          "2000" : 0.5
        } ]
      }
    }, {
      "48086" : {
        "title" : "Sopuerta",
        "values" : [ {
          "2019" : 4.3,
          "2018" : 3.97,
          "2017" : 4.14,
          "2016" : 3.8,
          "2015" : 3.5,
          "2012" : 3.5,
          "2010" : 3.1,
          "2008" : 2.5,
          "2005" : 3.2,
          "2000" : 5.8
        } ]
      }
    }, {
      "20065" : {
        "title" : "Soraluze-Placencia de las Armas",
        "values" : [ {
          "2019" : 0.77,
          "2018" : 0.59,
          "2017" : 0.79,
          "2016" : 0.6,
          "2015" : 0.5,
          "2012" : 0.4,
          "2010" : 0.4,
          "2008" : 0.3,
          "2005" : 0.4,
          "2000" : 0.7
        } ]
      }
    }, {
      "48076" : {
        "title" : "Sukarrieta",
        "values" : [ {
          "2019" : 1.15,
          "2018" : 0.9,
          "2017" : 0.98,
          "2016" : 0.6,
          "2015" : 0.4,
          "2012" : 0.5,
          "2010" : 0.4,
          "2008" : 0.6,
          "2005" : 0.3,
          "2000" : 0.8
        } ]
      }
    }, {
      "20071" : {
        "title" : "Tolosa",
        "values" : [ {
          "2019" : 0.34,
          "2018" : 0.29,
          "2017" : 0.39,
          "2016" : 0.4,
          "2015" : 0.4,
          "2012" : 0.4,
          "2010" : 0.4,
          "2008" : 0.4,
          "2005" : 0.5,
          "2000" : 0.4
        } ]
      }
    }, {
      "48087" : {
        "title" : "Trucios-Turtzioz",
        "values" : [ {
          "2019" : 13.58,
          "2018" : 12.09,
          "2017" : 11.17,
          "2016" : 10.1,
          "2015" : 8.5,
          "2012" : 9.4,
          "2010" : 8.7,
          "2008" : 9.2,
          "2005" : 13.5,
          "2000" : 23.4
        } ]
      }
    }, {
      "48088" : {
        "title" : "Ubide",
        "values" : [ {
          "2019" : 4.32,
          "2018" : 3.6,
          "2017" : 3.55,
          "2016" : 3.8,
          "2015" : 3.2,
          "2012" : 3.1,
          "2010" : 3.3,
          "2008" : 3.4,
          "2005" : 3.7,
          "2000" : 26.8
        } ]
      }
    }, {
      "48065" : {
        "title" : "Ugao-Miraballes",
        "values" : [ {
          "2019" : 0.34,
          "2018" : 0.28,
          "2017" : 0.31,
          "2016" : 0.3,
          "2015" : 0.3,
          "2012" : 0.3,
          "2010" : 0.2,
          "2008" : 0.2,
          "2005" : 0.3,
          "2000" : 0.4
        } ]
      }
    }, {
      "48089" : {
        "title" : "Urduliz",
        "values" : [ {
          "2019" : 0.21,
          "2018" : 0.25,
          "2017" : 0.37,
          "2016" : 0.6,
          "2015" : 0.4,
          "2012" : 0.3,
          "2010" : 0.2,
          "2008" : 0.5,
          "2005" : 0.6,
          "2000" : 2.4
        } ]
      }
    }, {
      "48074" : {
        "title" : "Urduña/Orduña",
        "values" : [ {
          "2019" : 4.41,
          "2018" : 3.91,
          "2017" : 4.31,
          "2016" : 3.9,
          "2015" : 3.5,
          "2012" : 3.2,
          "2010" : 3.1,
          "2008" : 3.6,
          "2005" : 2.8,
          "2000" : 2.5
        } ]
      }
    }, {
      "01054" : {
        "title" : "Urkabustaiz",
        "values" : [ {
          "2019" : 4.64,
          "2018" : 6.9,
          "2017" : 6.35,
          "2016" : 6.1,
          "2015" : 6.9,
          "2012" : 6.4,
          "2010" : 5.7,
          "2008" : 3.8,
          "2005" : 5.0,
          "2000" : 6.9
        } ]
      }
    }, {
      "20072" : {
        "title" : "Urnieta",
        "values" : [ {
          "2019" : 0.59,
          "2018" : 0.48,
          "2017" : 0.65,
          "2016" : 0.6,
          "2015" : 0.7,
          "2012" : 0.6,
          "2010" : 0.7,
          "2008" : 0.8,
          "2005" : 1.1,
          "2000" : 1.3
        } ]
      }
    }, {
      "20077" : {
        "title" : "Urretxu",
        "values" : [ {
          "2019" : 0.33,
          "2018" : 0.26,
          "2017" : 0.33,
          "2016" : 0.3,
          "2015" : 0.3,
          "2012" : 0.3,
          "2010" : 0.3,
          "2008" : 0.3,
          "2005" : 0.4,
          "2000" : 0.4
        } ]
      }
    }, {
      "20073" : {
        "title" : "Usurbil",
        "values" : [ {
          "2019" : 0.6,
          "2018" : 0.54,
          "2017" : 0.72,
          "2016" : 0.6,
          "2015" : 0.6,
          "2012" : 0.6,
          "2010" : 0.6,
          "2008" : 0.8,
          "2005" : 0.5,
          "2000" : 0.7
        } ]
      }
    }, {
      "01055" : {
        "title" : "Valdegovía/Gaubea",
        "values" : [ {
          "2019" : 20.55,
          "2018" : 19.79,
          "2017" : 18.7,
          "2016" : 19.0,
          "2015" : 19.6,
          "2012" : 18.6,
          "2010" : 16.3,
          "2008" : 13.4,
          "2005" : 14.2,
          "2000" : 24.3
        } ]
      }
    }, {
      "48080" : {
        "title" : "Valle de Trápaga-Trapagaran",
        "values" : [ {
          "2019" : 0.05,
          "2018" : 0.05,
          "2017" : 0.06,
          "2016" : 0.1,
          "2015" : 0.0,
          "2012" : 0.1,
          "2010" : 0.0,
          "2008" : 0.0,
          "2005" : 0.0,
          "2000" : 0.1
        } ]
      }
    }, {
      "20075" : {
        "title" : "Villabona",
        "values" : [ {
          "2019" : 0.56,
          "2018" : 0.48,
          "2017" : 0.62,
          "2016" : 0.6,
          "2015" : 0.6,
          "2012" : 0.6,
          "2010" : 0.6,
          "2008" : 0.5,
          "2005" : 0.8,
          "2000" : 0.8
        } ]
      }
    }, {
      "01057" : {
        "title" : "Villabuena de Álava/Eskuernaga",
        "values" : [ {
          "2019" : 13.85,
          "2018" : 16.21,
          "2017" : 13.77,
          "2016" : 15.4,
          "2015" : 15.3,
          "2012" : 7.6,
          "2010" : 8.8,
          "2008" : 13.6,
          "2005" : 15.1,
          "2000" : 47.3
        } ]
      }
    }, {
      "01059" : {
        "title" : "Vitoria-Gasteiz",
        "values" : [ {
          "2019" : 0.18,
          "2018" : 0.2,
          "2017" : 0.19,
          "2016" : 0.2,
          "2015" : 0.2,
          "2012" : 0.2,
          "2010" : 0.2,
          "2008" : 0.1,
          "2005" : 0.2,
          "2000" : 0.4
        } ]
      }
    }, {
      "01060" : {
        "title" : "Yécora/Iekora",
        "values" : [ {
          "2019" : 63.41,
          "2018" : 66.12,
          "2017" : 57.69,
          "2016" : 52.2,
          "2015" : 45.9,
          "2012" : 31.5,
          "2010" : 29.1,
          "2008" : 34.9,
          "2005" : 41.9,
          "2000" : 64.0
        } ]
      }
    }, {
      "48095" : {
        "title" : "Zaldibar",
        "values" : [ {
          "2019" : 0.45,
          "2018" : 0.4,
          "2017" : 0.41,
          "2016" : 0.5,
          "2015" : 0.5,
          "2012" : 0.4,
          "2010" : 0.4,
          "2008" : 0.2,
          "2005" : 0.3,
          "2000" : 1.1
        } ]
      }
    }, {
      "20078" : {
        "title" : "Zaldibia",
        "values" : [ {
          "2019" : 3.23,
          "2018" : 2.78,
          "2017" : 3.45,
          "2016" : 2.8,
          "2015" : 2.7,
          "2012" : 3.3,
          "2010" : 3.1,
          "2008" : 2.6,
          "2005" : 3.7,
          "2000" : 1.9
        } ]
      }
    }, {
      "01061" : {
        "title" : "Zalduondo",
        "values" : [ {
          "2019" : 25.8,
          "2018" : 27.09,
          "2017" : 24.61,
          "2016" : 27.3,
          "2015" : 29.5,
          "2012" : 26.2,
          "2010" : 30.5,
          "2008" : 28.1,
          "2005" : 29.3,
          "2000" : 36.2
        } ]
      }
    }, {
      "48096" : {
        "title" : "Zalla",
        "values" : [ {
          "2019" : 0.98,
          "2018" : 0.96,
          "2017" : 1.07,
          "2016" : 1.2,
          "2015" : 1.3,
          "2012" : 0.9,
          "2010" : 0.8,
          "2008" : 0.6,
          "2005" : 0.8,
          "2000" : 1.9
        } ]
      }
    }, {
      "01062" : {
        "title" : "Zambrana",
        "values" : [ {
          "2019" : 20.88,
          "2018" : 22.81,
          "2017" : 23.74,
          "2016" : 28.1,
          "2015" : 32.6,
          "2012" : 5.1,
          "2010" : 6.3,
          "2008" : 3.9,
          "2005" : 6.1,
          "2000" : 9.2
        } ]
      }
    }, {
      "48905" : {
        "title" : "Zamudio",
        "values" : [ {
          "2019" : 0.08,
          "2018" : 0.08,
          "2017" : 0.09,
          "2016" : 0.1,
          "2015" : 0.1,
          "2012" : 0.1,
          "2010" : 0.1,
          "2008" : 0.1,
          "2005" : 0.1,
          "2000" : 0.2
        } ]
      }
    }, {
      "48097" : {
        "title" : "Zaratamo",
        "values" : [ {
          "2019" : 1.21,
          "2018" : 1.08,
          "2017" : 1.38,
          "2016" : 1.4,
          "2015" : 1.2,
          "2012" : 1.4,
          "2010" : 1.2,
          "2008" : 0.8,
          "2005" : 1.0,
          "2000" : 0.6
        } ]
      }
    }, {
      "20079" : {
        "title" : "Zarautz",
        "values" : [ {
          "2019" : 0.45,
          "2018" : 0.45,
          "2017" : 0.54,
          "2016" : 0.4,
          "2015" : 0.5,
          "2012" : 0.6,
          "2010" : 0.4,
          "2008" : 0.4,
          "2005" : 0.5,
          "2000" : 0.3
        } ]
      }
    }, {
      "48024" : {
        "title" : "Zeanuri",
        "values" : [ {
          "2019" : 8.11,
          "2018" : 7.17,
          "2017" : 8.13,
          "2016" : 10.0,
          "2015" : 10.1,
          "2012" : 6.3,
          "2010" : 4.2,
          "2008" : 4.8,
          "2005" : 7.1,
          "2000" : 13.3
        } ]
      }
    }, {
      "48025" : {
        "title" : "Zeberio",
        "values" : [ {
          "2019" : 12.75,
          "2018" : 10.98,
          "2017" : 11.21,
          "2016" : 13.2,
          "2015" : 11.9,
          "2012" : 10.2,
          "2010" : 8.2,
          "2008" : 8.4,
          "2005" : 12.6,
          "2000" : 16.7
        } ]
      }
    }, {
      "20025" : {
        "title" : "Zegama",
        "values" : [ {
          "2019" : 3.79,
          "2018" : 2.64,
          "2017" : 3.98,
          "2016" : 3.3,
          "2015" : 4.1,
          "2012" : 3.8,
          "2010" : 4.6,
          "2008" : 3.1,
          "2005" : 4.2,
          "2000" : 6.2
        } ]
      }
    }, {
      "20026" : {
        "title" : "Zerain",
        "values" : [ {
          "2019" : 8.21,
          "2018" : 8.95,
          "2017" : 9.92,
          "2016" : 9.4,
          "2015" : 10.9,
          "2012" : 11.7,
          "2010" : 13.6,
          "2008" : 11.1,
          "2005" : 14.8,
          "2000" : 9.7
        } ]
      }
    }, {
      "20027" : {
        "title" : "Zestoa",
        "values" : [ {
          "2019" : 1.9,
          "2018" : 1.67,
          "2017" : 2.0,
          "2016" : 1.7,
          "2015" : 1.6,
          "2012" : 1.6,
          "2010" : 2.1,
          "2008" : 1.3,
          "2005" : 3.0,
          "2000" : 4.1
        } ]
      }
    }, {
      "48913" : {
        "title" : "Zierbena",
        "values" : [ {
          "2019" : 0.91,
          "2018" : 0.41,
          "2017" : 0.6,
          "2016" : 0.8,
          "2015" : 0.6,
          "2012" : 0.6,
          "2010" : 0.4,
          "2008" : 0.4,
          "2005" : 0.4,
          "2000" : 1.9
        } ]
      }
    }, {
      "01018" : {
        "title" : "Zigoitia",
        "values" : [ {
          "2019" : 2.84,
          "2018" : 3.5,
          "2017" : 3.35,
          "2016" : 2.9,
          "2015" : 2.7,
          "2012" : 4.5,
          "2010" : 3.4,
          "2008" : 2.1,
          "2005" : 2.8,
          "2000" : 6.5
        } ]
      }
    }, {
      "48915" : {
        "title" : "Ziortza-Bolibar",
        "values" : [ {
          "2019" : 9.18,
          "2018" : 7.87,
          "2017" : 7.87,
          "2016" : 7.2,
          "2015" : 7.0,
          "2012" : 6.6,
          "2010" : 5.3,
          "2008" : 3.4,
          "2005" : 0.0,
          "2000" : 0.0
        } ]
      }
    }, {
      "20028" : {
        "title" : "Zizurkil",
        "values" : [ {
          "2019" : 1.12,
          "2018" : 0.94,
          "2017" : 1.17,
          "2016" : 1.1,
          "2015" : 1.2,
          "2012" : 1.1,
          "2010" : 1.1,
          "2008" : 1.5,
          "2005" : 2.2,
          "2000" : 2.7
        } ]
      }
    }, {
      "01063" : {
        "title" : "Zuia",
        "values" : [ {
          "2019" : 3.19,
          "2018" : 4.72,
          "2017" : 4.12,
          "2016" : 3.9,
          "2015" : 3.9,
          "2012" : 3.8,
          "2010" : 3.6,
          "2008" : 2.5,
          "2005" : 5.0,
          "2000" : 8.8
        } ]
      }
    }, {
      "20081" : {
        "title" : "Zumaia",
        "values" : [ {
          "2019" : 0.34,
          "2018" : 0.32,
          "2017" : 0.41,
          "2016" : 0.3,
          "2015" : 0.3,
          "2012" : 0.3,
          "2010" : 0.3,
          "2008" : 0.4,
          "2005" : 0.4,
          "2000" : 0.6
        } ]
      }
    }, {
      "20080" : {
        "title" : "Zumarraga",
        "values" : [ {
          "2019" : 0.39,
          "2018" : 0.3,
          "2017" : 0.38,
          "2016" : 0.3,
          "2015" : 0.3,
          "2012" : 0.2,
          "2010" : 0.3,
          "2008" : 0.3,
          "2005" : 0.4,
          "2000" : 0.5
        } ]
      }
    } ]
  }]
}
  